Workbook

Sheet README
A1: Washington, D.C. streetcar lines, 1862–1962
A3: Sheets
A4: Chronology: 176 dated events (charters, openings, extensions, power changes, closures), sorted by year and keyed to Line IDs.
A5: Route Numbers 1936-62: every Capital Transit / D.C. Transit streetcar route number with termini, the 1946 street-by-street routing (Tundria) where known, and end dates. Routes 40/42 corrected in version 5.
A6: Track Ways: the network as a node-and-way model, split into stretches of physical track. Each stretch is one way tagged railway=tram with start_date and end_date; the lines that run over it are route relations (type=route, route=tram), whose tags are in the Lines sheet. Shared stretches are listed first. The same model is exported as dc_streetcars_OHM_draft.osm.
A7: Relations: each line is a type=chronology relation listing its dated route relations in order. Each dated route (type=route, route=tram) covers a period in which the line used the same set of ways, with the same operator and motive power (railway:traction), and carries its own start_date and end_date. A way records only when the track itself existed, so one way can belong to different routes in different periods.
A8: Track Nodes: tagged nodes in the track network: railway=railway_crossing where two tracks cross at grade (dated to the years both tracks existed) and railway=switch where tracks branch.
A9: 1905 Franchise Laws: acts of Congress and charters for lines that were actually built, with the authorized route trimmed to the portion that was built, and the matching Line ID.
A10: Research Notes: source conflicts, corrections made in this version, unreliable sources, gaps, and primary sources worth mining next.
A11: Lines: one row per line, branch or extension, with streets, company, motive power, opening and closing dates, and 1936+ route numbers. The four right-hand columns give the length of track drawn for the line, how much of it is shared, the lines it shares track with, and its route relation tags in OHM form. The numeric 'First year' and 'Year service ended' columns are there for time-slider mapping.
A12: Summary: counts of lines opened and ended by decade (live formulas from the Lines sheet).
A13: CTC Route Table: the chicagorailfan.com line-by-line table (horse, cable and electric start years plus bus conversion date), with duplicates removed.
... A23: Compiled Sept 24, 2026. Version 7 is limited to lines, extensions and events that were actually built: unbuilt charters, proposals and routes have been removed. Version 5 added findings from reviewing the 1880, 1891, 1910, 1924, 1942, 1946 and 1958 maps: corrected route termini, three new line rows (L56–L58), and the Rand McNally map series.

Sheet Summary
A1: Lines by decade (formulas read the Lines sheet)
A3: Decade start | B3: Lines opened | C3: Lines ended | D3: Net change
A4: 1860 | B4: =COUNTIFS(Lines!$H$2:$H$66,">="&A4,Lines!$H$2:$H$66,"<"&A4+10) -> 5 | C4: =COUNTIFS(Lines!$N$2:$N$66,">="&A4,Lines!$N$2:$N$66,"<"&A4+10) -> 0 | D4: =B4-C4 -> 5
A5: 1870 | B5: =COUNTIFS(Lines!$H$2:$H$66,">="&A5,Lines!$H$2:$H$66,"<"&A5+10) -> 11 | C5: =COUNTIFS(Lines!$N$2:$N$66,">="&A5,Lines!$N$2:$N$66,"<"&A5+10) -> 0 | D5: =B5-C5 -> 11
A6: 1880 | B6: =COUNTIFS(Lines!$H$2:$H$66,">="&A6,Lines!$H$2:$H$66,"<"&A6+10) -> 3 | C6: =COUNTIFS(Lines!$N$2:$N$66,">="&A6,Lines!$N$2:$N$66,"<"&A6+10) -> 0 | D6: =B6-C6 -> 3
A7: 1890 | B7: =COUNTIFS(Lines!$H$2:$H$66,">="&A7,Lines!$H$2:$H$66,"<"&A7+10) -> 24 | C7: =COUNTIFS(Lines!$N$2:$N$66,">="&A7,Lines!$N$2:$N$66,"<"&A7+10) -> 2 | D7: =B7-C7 -> 22
A8: 1900 | B8: =COUNTIFS(Lines!$H$2:$H$66,">="&A8,Lines!$H$2:$H$66,"<"&A8+10) -> 12 | C8: =COUNTIFS(Lines!$N$2:$N$66,">="&A8,Lines!$N$2:$N$66,"<"&A8+10) -> 1 | D8: =B8-C8 -> 11
A9: 1910 | B9: =COUNTIFS(Lines!$H$2:$H$66,">="&A9,Lines!$H$2:$H$66,"<"&A9+10) -> 5 | C9: =COUNTIFS(Lines!$N$2:$N$66,">="&A9,Lines!$N$2:$N$66,"<"&A9+10) -> 0 | D9: =B9-C9 -> 5
A10: 1920 | B10: =COUNTIFS(Lines!$H$2:$H$66,">="&A10,Lines!$H$2:$H$66,"<"&A10+10) -> 1 | C10: =COUNTIFS(Lines!$N$2:$N$66,">="&A10,Lines!$N$2:$N$66,"<"&A10+10) -> 10 | D10: =B10-C10 -> -9
A11: 1930 | B11: =COUNTIFS(Lines!$H$2:$H$66,">="&A11,Lines!$H$2:$H$66,"<"&A11+10) -> 1 | C11: =COUNTIFS(Lines!$N$2:$N$66,">="&A11,Lines!$N$2:$N$66,"<"&A11+10) -> 14 | D11: =B11-C11 -> -13
A12: 1940 | B12: =COUNTIFS(Lines!$H$2:$H$66,">="&A12,Lines!$H$2:$H$66,"<"&A12+10) -> 0 | C12: =COUNTIFS(Lines!$N$2:$N$66,">="&A12,Lines!$N$2:$N$66,"<"&A12+10) -> 5 | D12: =B12-C12 -> -5
A13: 1950 | B13: =COUNTIFS(Lines!$H$2:$H$66,">="&A13,Lines!$H$2:$H$66,"<"&A13+10) -> 0 | C13: =COUNTIFS(Lines!$N$2:$N$66,">="&A13,Lines!$N$2:$N$66,"<"&A13+10) -> 4 | D13: =B13-C13 -> -4
A14: 1960 | B14: =COUNTIFS(Lines!$H$2:$H$66,">="&A14,Lines!$H$2:$H$66,"<"&A14+10) -> 0 | C14: =COUNTIFS(Lines!$N$2:$N$66,">="&A14,Lines!$N$2:$N$66,"<"&A14+10) -> 21 | D14: =B14-C14 -> -21
A15: Total | B15: =SUM(B4:B14) -> 62 | C15: =SUM(C4:C14) -> 57 | D15: =B15-C15 -> 5
A17: Lines with no end year recorded | C17: =COUNTA(Lines!$A$2:$A$66)-COUNT(Lines!$N$2:$N$66) -> 8
A18: Total rows in Lines sheet | C18: =COUNTA(Lines!$A$2:$A$66) -> 65
A20: Counts are by segment/row, not by company; a line split into branches counts once per branch.

Sheet Lines
A1: ID | B1: Line / corridor | C1: Streets & termini (as described in sources) | D1: Jurisdiction | E1: Original company | F1: Later operators | G1: Motive power history | H1: First year of rail service | I1: Horse cars from | J1: Cable from | K1: Electric from | L1: Capital Transit route no(s). (1936+) | M1: Streetcar service ended | N1: Year service ended | O1: Replaced by | P1: Notes | Q1: Sources | R1: Track drawn (km) | S1: Of which shared (km) | T1: Shares track with | U1: Chronology and dated routes (OHM)
A2: L01 | B2: Pennsylvania Avenue line (Georgetown–Navy Yard) | C2: M St NW (Georgetown) – Pennsylvania Ave NW/SE – Navy Yard; extended 1895 from 32nd St to 36th & M St (Georgetown Car Barn); extended on Pennsylvania Ave SE from 8th St to 17th St SE in 1901, later to Barney Circle | D2: DC | E2: Washington & Georgetown Railroad | F2: Capital Traction (1895); Capital Transit (1933); D.C. Transit (1956) | G2: Horse → cable (1892) → horse again after Sept 1897 powerhouse fire → underground conduit electric (1898) | H2: 1862 | I2: 1862 | J2: 1892 | K2: 1898 | L2: 30 (Wisconsin Ave–Pennsylvania Ave SE); 54 (14th St–Pennsylvania Ave to Navy Yard) | M2: Route 30: Jan 3, 1960; Route 54: Jan 28, 1962 | N2: 1962 | O2: Bus routes 30s / 54 | P2: Capitol–White House July 29, 1862; Washington Circle Aug 12; Georgetown Aug 18; Navy Yard Oct 2. Electrified Apr 20, 1898. West End loop 1901. West End loops: see L56. Map: westbound cars used a Wisconsin Ave, Prospect St and 34th St loop in 1946 (Tundria), and the line used M St and 26th St between 1875 and 1916 (1880 map). 1912 map (audit): the 1901 extension ended in a loop around the block at 15th St SE. | Q2: WP; MPD; CRF | R2: 11.73 | S2: 2.74 | T2: L02, L05, L18, L22, L32, L34, L36, L56 | U2: type=chronology name=Pennsylvania Avenue line (Georgetown–Navy Yard) network=Washington, D.C. streetcars operator=Washington & Georgetown Railroad start_date=1862 end_date=1962 ref:streetcar_project=L01 ref=30;54 description=Later operators: Capital Traction (1895); Capital Transit (1933); D.C. Transit (1956) source=WP; MPD; CRF Dated route relations in this chronology: 1862–1875: 24 ways; operator=Washington & Georgetown Railroad; railway:traction=horse 1875–1892: 25 ways; operator=Washington & Georgetown Railroad; railway:traction=horse 1892–1895: 25 ways; operator=Washington & Georgetown Railroad; railway:traction=cable 1895–1898: 28 ways; operator=Capital Traction; railway:traction=cable 1898–1901: 28 ways; operator=Capital Traction; railway:traction=electric 1901–1916: 30 ways; operator=Capital Traction; railway:traction=electric 1916–1934: 29 ways; operator=Capital Traction; railway:traction=electric 1934–1936: 29 ways; operator=Capital Transit; railway:traction=electric 1936–1956: 31 ways; operator=Capital Transit; railway:traction=electric 1956–1960: 31 ways; operator=D.C. Transit; railway:traction=electric 1960–1962: 29 ways; operator=D.C. Transit; railway:traction=electric
A3: L02 | B3: 7th Street line | C3: 7th St NW/SW from Boundary St (Florida Ave) to the Potomac wharves; extended to the Arsenal (Fort McNair) in 1875; ran along M St SW to 7th St | D3: DC | E3: Washington & Georgetown Railroad | F3: Capital Traction (1895); Capital Transit; D.C. Transit | G3: Horse → cable (May 12, 1890, DC's first cable line) → horse after 1897 fire → electric conduit (1898) | H3: 1862 | I3: 1862 | J3: 1890 | K3: 1898 | L3: 70 (7th St–Georgia Ave); 76, 78 (to wharves, 1936) | M3: Jan 3, 1960 | N3: 1960 | O3: Bus route 70 | P3: Opened Nov 15, 1862. DC's first cable line (Apr 12, 1890 per Wikipedia; May 12 per NRHP). Electrified May 26, 1898. Cable powerhouse at P & Water Sts SW. 1912 map: south of M St the line ran along the old Water St beside the Washington Channel to P St and the Arsenal gate (the modern Maine Ave and Wharf streets are drawn differently, so this stretch is drawn straight). | Q3: WP; MPD; CRF; GDC | R3: 7.23 | S3: 1.94 | T3: L01, L08, L18, L22, L34 | U3: type=chronology name=7th Street line network=Washington, D.C. streetcars operator=Washington & Georgetown Railroad start_date=1862 end_date=1960 ref:streetcar_project=L02 ref=70;76;78 description=Later operators: Capital Traction (1895); Capital Transit; D.C. Transit source=WP; MPD; CRF; GDC Dated route relations in this chronology: 1862–1875: 15 ways; operator=Washington & Georgetown Railroad; railway:traction=horse 1875–1890: 17 ways; operator=Washington & Georgetown Railroad; railway:traction=horse 1890–1895: 17 ways; operator=Washington & Georgetown Railroad; railway:traction=cable 1895–1898: 17 ways; operator=Capital Traction; railway:traction=cable 1898–1934: 17 ways; operator=Capital Traction; railway:traction=electric 1934–1941: 17 ways; operator=Capital Transit; railway:traction=electric 1941–1956: 27 ways; operator=Capital Transit; railway:traction=electric 1956–1960: 27 ways; operator=D.C. Transit; railway:traction=electric
A4: L03 | B4: 14th Street line | C4: 14th St NW from Boundary St to the Treasury (15th St & New York Ave); extended up the hill to Park Rd (Mount Pleasant) c.1892–95; extended to Colorado Ave 1906–07 (Decatur St car barn); Colorado Ave terminal by 1937 | D4: DC | E4: Washington & Georgetown Railroad | F4: Capital Traction (1895); Capital Transit; D.C. Transit | G4: Horse → cable (1892; CRF lists 1895) → electric conduit (1898) | H4: 1862 | I4: 1862 | J4: 1892 | K4: 1898 | L4: 50 (to Bureau of Engraving); 52; 54 (to Navy Yard) | M4: Jan 28, 1962 (last line in DC) | N4: 1962 | O4: Bus routes 50s | P4: Electrified Feb 27, 1898. First PCC cars Aug 1937. Last scheduled run left 14th & Colorado 2:17 am, Jan 28, 1962. | Q4: WP; MPD; CRF | R4: 6.38 | S4: 0.16 | T4: L15 | U4: type=chronology name=14th Street line network=Washington, D.C. streetcars operator=Washington & Georgetown Railroad start_date=1862 end_date=1962 ref:streetcar_project=L03 ref=50;52;54 description=Later operators: Capital Traction (1895); Capital Transit; D.C. Transit source=WP; MPD; CRF Dated route relations in this chronology: 1862–1892: 4 ways; operator=Washington & Georgetown Railroad; railway:traction=horse 1892–1895: 5 ways; operator=Washington & Georgetown Railroad; railway:traction=cable 1895–1898: 5 ways; operator=Capital Traction; railway:traction=cable 1898–1906: 5 ways; operator=Capital Traction; railway:traction=electric 1906–1907: 6 ways; operator=Capital Traction; railway:traction=electric 1907–1934: 7 ways; operator=Capital Traction; railway:traction=electric 1934–1956: 7 ways; operator=Capital Transit; railway:traction=electric 1956–1962: 7 ways; operator=D.C. Transit; railway:traction=electric
A5: L04 | B5: Georgetown–B&O Depot (Capitol Hill) line | C5: Georgetown to the B&O depot at New Jersey Ave & C St NW; later Mount Pleasant–B&O Depot via Pennsylvania Ave and 14th St (cable era) | D5: DC | E5: Washington & Georgetown Railroad | F5: Capital Traction (1895) | G5: Horse → cable → electric | H5: 1862 | I5: 1862 | J5: 1892 | K5: 1898 | L5: — | M5: Absorbed into other routes (depot razed after 1907) | O5: — | P5: One of four W&G services in 1863 (21 cars). | Q5: MPD | R5: 0.42 | S5: 0.4 | T5: L22, L55, L58 | U5: type=chronology name=Georgetown–B&O Depot (Capitol Hill) line network=Washington, D.C. streetcars operator=Washington & Georgetown Railroad start_date=1862 end_date=1908 ref:streetcar_project=L04 end_date:edtf=1908~ description=Later operators: Capital Traction (1895) source=MPD Dated route relations in this chronology: 1862–1892: 6 ways; operator=Washington & Georgetown Railroad; railway:traction=horse 1892–1895: 6 ways; operator=Washington & Georgetown Railroad; railway:traction=cable 1895–1898: 6 ways; operator=Capital Traction; railway:traction=cable 1898–1908: 6 ways; operator=Capital Traction; railway:traction=electric
A6: L05 | B6: Metropolitan main line (Capitol–War Dept; later F St/D St line) | C6: Charter route (1864): A St & New Jersey Ave via D, C, Indiana Ave, 5th, F and 14th Sts. As built (Jan 1865): Capitol to 14th & I Sts NW, plus H St NW from Massachusetts Ave to 17th St | D6: DC | E6: Metropolitan Railroad | F6: Washington Traction & Electric (1899); WRECo (1902); Capital Transit; D.C. Transit | G6: Horse → electric conduit (1896) | H6: 1865 | I6: 1865 | J6: — | K6: 1896 | L6: 42 (Mt. Pleasant); D6 bus later | M6: Dec 3, 1961 | N6: 1961 | O6: Bus D6 / 42 | P6: CRF dates horse service 1865. 1912 map: a link ran along Indiana Ave from D St to C St at 1st St NW. | Q6: WP; MPD; CRF | R6: 5.29 | S6: 0.16 | T6: L01 | U6: type=chronology name=Metropolitan main line (Capitol–War Dept; later F St/D St line) network=Washington, D.C. streetcars operator=Metropolitan Railroad start_date=1865 end_date=1961 ref:streetcar_project=L05 ref=42 description=Later operators: Washington Traction & Electric (1899); WRECo (1902); Capital Transit; D.C. Transit source=WP; MPD; CRF Dated route relations in this chronology: 1865–1896: 22 ways; operator=Metropolitan Railroad; railway:traction=horse 1896–1902: 22 ways; operator=Metropolitan Railroad; railway:traction=electric 1902–1934: 22 ways; operator=Washington Railway & Electric; railway:traction=electric 1934–1956: 22 ways; operator=Capital Transit; railway:traction=electric 1956–1961: 22 ways; operator=D.C. Transit; railway:traction=electric
A7: L06 | B7: 9th Street line | C7: 9th St NW north from M St to Boundary St, joining the Boundary & Silver Spring line | D7: DC | E7: Metropolitan Railroad | F7: WRECo (1902); Capital Transit | G7: Horse (1872) → first underground-conduit electric line in DC (1895) | H7: 1872 | I7: 1872 | J7: — | K7: 1895 | L7: — | M7: 1933 (NRHP) or 1936 (Ghosts of DC) | N7: 1933 | O7: Buses | P7: Sources disagree on the conversion year: NRHP says 1933 with the rebuilding of 9th St; Ghosts of DC says cars were pulled in 1936. Map: 9th St track continued south to Pennsylvania Ave (1912 map); route 40 ran via 9th St, Pennsylvania Ave and C St NW in 1946. 1912 map: north of Florida Ave the 9th St track curved northwest to join the 11th St line near Kenyon St (date of this curve not documented). | Q7: MPD; GDC | R7: 4.01 | S7: 0.15 | T7: L15, L31 | U7: type=chronology name=9th Street line network=Washington, D.C. streetcars operator=Metropolitan Railroad start_date=1872 end_date=1961 ref:streetcar_project=L06 description=Later operators: WRECo (1902); Capital Transit source=MPD; GDC Dated route relations in this chronology: 1872–1895: 11 ways; operator=Metropolitan Railroad; railway:traction=horse 1895–1902: 11 ways; operator=Metropolitan Railroad; railway:traction=electric 1902–1933: 11 ways; operator=Washington Railway & Electric; railway:traction=electric 1936–1961: 1 ways; operator=Capital Transit; railway:traction=electric
A8: L07 | B8: P Street / Georgetown line | C8: P St NW west from Dupont Circle to Georgetown (36th & Prospect St), built under the Union Railroad charter; completed 1880 | D8: DC | E8: Metropolitan Railroad (Union Railroad charter) | F8: WRECo; Capital Transit | G8: Horse → battery trials (1891–93) → electric conduit (1896) | H8: 1873 | I8: 1873 | J8: — | K8: 1896 | L8: — (bus G2) | M8: June 16, 1935 | N8: 1935 | O8: Bus G2 | P8: Union RR absorbed Aug–Nov 1872 without authority. Georgetown loop on P, 36th, Prospect and 35th Sts authorized 1895. Rails remain on O & P Sts between 33rd and 35th Sts NW. Map: the Georgetown P and O St loop west of Wisconsin Ave stayed in use for Cabin John cars until 1960 (1958 trackage map). 1912 map: a loop east of Wisconsin Ave ran via P St, 28th St and Dumbarton St. 1912 map (Georgetown): cars ran out P St to 36th St, down to the car barn at Prospect St, along Prospect and up 35th St, then east on O St across Wisconsin Ave into Dumbarton St and back up 28th St. The original 1873 loop used P, 35th, O and 33rd Sts; the O St and P St loop west of Wisconsin was later the Cabin John cars' terminal (1935–60, from the 1958 trackage map). | Q8: WP; MPD; CRF | R8: 4.57 | S8: 1.74 | T8: L36, L39 | U8: type=chronology name=P Street / Georgetown line network=Washington, D.C. streetcars operator=Metropolitan Railroad (Union Railroad charter) start_date=1873 end_date=1935 ref:streetcar_project=L07 description=Later operators: WRECo; Capital Transit source=WP; MPD; CRF Dated route relations in this chronology: 1873–1896: 10 ways; operator=Metropolitan Railroad; railway:traction=horse 1896–1902: 10 ways; operator=Metropolitan Railroad; railway:traction=electric 1902–1934: 10 ways; operator=Washington Railway & Electric; railway:traction=electric 1934–1935: 10 ways; operator=Capital Transit; railway:traction=electric
A9: L08 | B9: 4th Street NW/SW line | C9: 4½ St (now 4th St) SW from Missouri Ave to P St SW / Arsenal; reached via unauthorized tracks on B St, 6th St and Missouri Ave | D9: DC | E9: Metropolitan Railroad | F9: WRECo; Capital Transit | G9: Horse → electric (1895) | H9: 1872 | I9: 1872 | J9: — | K9: 1895 | L9: — (buses V2/M2) | M9: 1930s | N9: 1935 | O9: Bus M2 | P9: CRF gives '1930s' only; end year approximate. Map: reached 4½ St via 9th St, B St (Constitution Ave), 6th St and Missouri Ave (1880 and 1912 maps). 1912 map: 4½ St is today's 4th St SW; the line ran down Missouri Ave from 6th & B Sts onto it. | Q9: WP; CRF | R9: 2.72 | S9: 2.04 | T9: L02, L18 | U9: type=chronology name=4th Street NW/SW line network=Washington, D.C. streetcars operator=Metropolitan Railroad start_date=1872 end_date=1935 ref:streetcar_project=L08 description=Later operators: WRECo; Capital Transit source=WP; CRF Dated route relations in this chronology: 1872–1895: 7 ways; operator=Metropolitan Railroad; railway:traction=horse 1895–1902: 7 ways; operator=Metropolitan Railroad; railway:traction=electric 1902–1934: 7 ways; operator=Washington Railway & Electric; railway:traction=electric 1934–1935: 7 ways; operator=Capital Transit; railway:traction=electric
A10: L09 | B10: East Capitol Street line | C10: East Capitol St to 9th St (by 1888); extended 1896 to the East Capitol St car barn / Lincoln Park loop (1400 East Capitol St) | D10: DC | E10: Metropolitan Railroad | F10: WRECo; Capital Transit; D.C. Transit | G10: Horse → electric conduit (1896) | H10: 1872 | I10: 1872 | J10: — | K10: 1896 | L10: 40 (Lincoln Park); 96 bus later | M10: Jan 28, 1962 | N10: 1962 | O10: Bus 96 | P10: One of the last two car barns in service (Lincoln Park). Map: reached East Capitol St via C St, Delaware Ave, B St (Constitution Ave) and 1st St NE (1880 map). 1912 map: tracks ran around both sides of Lincoln Park and ended in a loop around the block east of the park. | Q10: WP; MPD; CRF | R10: 3.65 | S10: 0.5 | T10: L34, L55 | U10: type=chronology name=East Capitol Street line network=Washington, D.C. streetcars operator=Metropolitan Railroad start_date=1872 end_date=1962 ref:streetcar_project=L09 ref=40;96 description=Later operators: WRECo; Capital Transit; D.C. Transit source=WP; MPD; CRF Dated route relations in this chronology: 1872–1896: 6 ways; operator=Metropolitan Railroad; railway:traction=horse 1896–1902: 11 ways; operator=Metropolitan Railroad; railway:traction=electric 1902–1934: 11 ways; operator=Washington Railway & Electric; railway:traction=electric 1934–1956: 11 ways; operator=Capital Transit; railway:traction=electric 1956–1962: 11 ways; operator=D.C. Transit; railway:traction=electric
A11: L10 | B11: Connecticut Avenue line (south) | C11: Connecticut Ave from 17th St & New York Ave / White House north to Boundary St (Florida Ave) | D11: DC | E11: Connecticut Avenue & Park Railway (chartered 1868) | F11: Metropolitan (1874); WRECo; Capital Transit; D.C. Transit | G11: Horse (April 1873) → electric (1896) | H11: 1873 | I11: 1873 | J11: — | K11: 1896 | L11: 42, 44 | M11: Dec 3, 1961 | N11: 1961 | O11: Bus 42 | P11: Horsecars ran only to P St in 1873; the track north to Florida Ave was paved over and then revived as a shuttle in 1883. Dupont Circle underpass opened Nov 2, 1949. Conflict: the 1880 statistical map shows track on Connecticut Ave to S St, although Tindall and Wikipedia say the section north of P St was paved over until 1883. 1912 map: the line ran on 17th St between H St and K St, joining Connecticut Ave at Farragut Square. | Q11: WP; MPD; CRF; MAP1880 | R11: 1.91 | S11: 0 | T11: — | U11: type=chronology name=Connecticut Avenue line (south) network=Washington, D.C. streetcars operator=Connecticut Avenue & Park Railway (chartered 1868) start_date=1873 end_date=1961 ref:streetcar_project=L10 ref=42;44 description=Later operators: Metropolitan (1874); WRECo; Capital Transit; D.C. Transit source=WP; MPD; CRF; MAP1880 Dated route relations in this chronology: 1873–1883: 2 ways; operator=Connecticut Avenue & Park Railway; railway:traction=horse 1883–1896: 4 ways; operator=Connecticut Avenue & Park Railway; railway:traction=horse 1896–1902: 4 ways; operator=Connecticut Avenue & Park Railway; railway:traction=electric 1902–1934: 4 ways; operator=Washington Railway & Electric; railway:traction=electric 1934–1956: 4 ways; operator=Capital Transit; railway:traction=electric 1956–1961: 4 ways; operator=D.C. Transit; railway:traction=electric
A12: L11 | B12: Mount Pleasant extension | C12: Columbia Rd from Connecticut & Florida Aves to 18th St (1897), then Columbia Rd east to 'old Sixteenth St' (today's Mount Pleasant St) and north to Park St (1900) | D12: DC | E12: Metropolitan Railroad | F12: WRECo; Capital Transit; D.C. Transit | G12: Electric | H12: 1900 | I12: — | J12: — | K12: 1900 | L12: 42 (Mt. Pleasant) | M12: Dec 3, 1961 | N12: 1961 | O12: Bus 42/43 | P12: Authorized Feb 27, 1897; service began June 6, 1900 (the earlier 1896 date was wrong). | Q12: WP-Metro; TIN; LAWS; CRF | R12: 2.39 | S12: 0 | T12: — | U12: type=chronology name=Mount Pleasant extension network=Washington, D.C. streetcars operator=Metropolitan Railroad start_date=1900 end_date=1961 ref:streetcar_project=L11 ref=42 description=Later operators: WRECo; Capital Transit; D.C. Transit source=WP-Metro; TIN; LAWS; CRF Dated route relations in this chronology: 1900–1902: 2 ways; operator=Metropolitan Railroad; railway:traction=electric 1902–1934: 2 ways; operator=Washington Railway & Electric; railway:traction=electric 1934–1956: 2 ways; operator=Capital Transit; railway:traction=electric 1956–1961: 2 ways; operator=D.C. Transit; railway:traction=electric
A13: L12 | B13: Georgia Avenue (7th St Extended / Brightwood) line | C13: Georgia Ave (Brightwood Ave) from Florida Ave to Rock Creek Church Rd (horse, 1873), then to Brightwood and the Silver Spring district line | D13: DC | E13: Boundary & Silver Spring Railway (chartered 1872; bought by Metropolitan Dec 1872) | F13: Brightwood Railway (1888/1890); WRECo; Capital Transit; D.C. Transit | G13: Horse → Judson pneumatic trial (1889–90, failed) → overhead electric ordered 1892 → underground conduit ordered 1898 | H13: 1873 | I13: 1873 | J13: — | K13: 1890 | L13: 70 (Georgia Ave to Brightwood) | M13: Jan 3, 1960 | N13: 1960 | O13: Bus 70 | P13: CRF gives electric 1890; Wikipedia says Congress ordered overhead electric in 1892. The 1880 map (and Berman's 2019 redraw) labels the city end of this line 'Pleasant Plains', possibly because the map stops at the city limit. | Q13: WP; MPD; CRF | R13: 7.61 | S13: 0.06 | T13: L41 | U13: type=chronology name=Georgia Avenue (7th St Extended / Brightwood) line network=Washington, D.C. streetcars operator=Boundary & Silver Spring Railway (chartered 1872; bought by Metropolitan Dec 1872) start_date=1873 end_date=1960 ref:streetcar_project=L12 ref=70 description=Later operators: Brightwood Railway (1888/1890); WRECo; Capital Transit; D.C. Transit source=WP; MPD; CRF Dated route relations in this chronology: 1873–1890: 4 ways; operator=Boundary & Silver Spring Railway; railway:traction=horse 1890–1893: 7 ways; operator=Boundary & Silver Spring Railway; railway:traction=electric 1893–1902: 10 ways; operator=Boundary & Silver Spring Railway; railway:traction=electric 1902–1934: 10 ways; operator=Washington Railway & Electric; railway:traction=electric 1934–1956: 10 ways; operator=Capital Transit; railway:traction=electric 1956–1960: 10 ways; operator=D.C. Transit; railway:traction=electric
A14: L13 | B14: Takoma branch (Brightwood Railway) | C14: Georgia Ave to Butternut St (then Umatilla St) and 4th St NW, Takoma Park | D14: DC | E14: Brightwood Railway | F14: WRECo; Capital Transit; D.C. Transit | G14: Electric | H14: 1893 | I14: — | J14: — | K14: 1892 | L14: 72 (Georgia Ave–Takoma) | M14: Jan 3, 1960 | N14: 1960 | O14: Bus 52/54 | Q14: WP; CRF | R14: 0.77 | S14: 0 | T14: — | U14: type=chronology name=Takoma branch (Brightwood Railway) network=Washington, D.C. streetcars operator=Brightwood Railway start_date=1893 end_date=1960 ref:streetcar_project=L13 ref=72 description=Later operators: WRECo; Capital Transit; D.C. Transit source=WP; CRF Dated route relations in this chronology: 1893–1902: 1 ways; operator=Brightwood Railway; railway:traction=electric 1902–1934: 1 ways; operator=Washington Railway & Electric; railway:traction=electric 1934–1956: 1 ways; operator=Capital Transit; railway:traction=electric 1956–1960: 1 ways; operator=D.C. Transit; railway:traction=electric
A15: L14 | B15: Soldiers' Home / Upshur Street line | C15: Soldiers' Home by a route off Georgia Ave; CRF also lists an Upshur St line on old route 74 | D15: DC | E15: WRECo predecessor (not identified) | F15: WRECo; Capital Transit; D.C. Transit | G15: Electric | H15: 1893 | I15: — | J15: — | K15: 1893 | L15: 74 | M15: Jan 3, 1960 | N15: 1960 | O15: Bus 60 | P15: The original builder isn't named in the sources checked. | Q15: CRF; GDC | R15: 1.06 | S15: 0 | T15: — | U15: type=chronology name=Soldiers' Home / Upshur Street line network=Washington, D.C. streetcars operator=WRECo predecessor (not identified) start_date=1893 end_date=1960 ref:streetcar_project=L14 ref=74 description=Later operators: WRECo; Capital Transit; D.C. Transit source=CRF; GDC Dated route relations in this chronology: 1893–1902: 1 ways; operator=WRECo predecessor; railway:traction=electric 1902–1934: 1 ways; operator=Washington Railway & Electric; railway:traction=electric 1934–1956: 1 ways; operator=Capital Transit; railway:traction=electric 1956–1960: 1 ways; operator=D.C. Transit; railway:traction=electric
A16: L15 | B16: Columbia Railway – H Street line | C16: Charter route: 15th St & New York Ave NW via New York Ave, K St, Massachusetts Ave and H St NW/NE to 15th St NE | D16: DC | E16: Columbia Railway | F16: Washington Traction & Electric (1899); WRECo (1902); Capital Transit | G16: Horse → cable (Mar 9, 1895; the last cable line built in the US) → electric (July 22, 1899) | H16: 1870 | I16: 1870/1871 | J16: 1895 | K16: 1899 | L16: 10 (Rosslyn–Benning via H St) | M16: May 1, 1949 | N16: 1949 | O16: Bus X2 | P16: The last cable car in DC ran July 23, 1899. Revived as the DC Streetcar (2016–2026). Tundria: H St–Benning Rd track closed May 1, 1949. | Q16: WP; MPD; CRF | R16: 4.56 | S16: 0.22 | T16: L03, L06 | U16: type=chronology name=Columbia Railway – H Street line network=Washington, D.C. streetcars operator=Columbia Railway start_date=1870 end_date=1949 ref:streetcar_project=L15 ref=10 description=Later operators: Washington Traction & Electric (1899); WRECo (1902); Capital Transit source=WP; MPD; CRF Dated route relations in this chronology: 1870–1895: 13 ways; operator=Columbia Railway; railway:traction=horse 1895–1899: 13 ways; operator=Columbia Railway; railway:traction=cable 1899–1902: 13 ways; operator=Columbia Railway; railway:traction=electric 1902–1934: 13 ways; operator=Washington Railway & Electric; railway:traction=electric 1934–1949: 13 ways; operator=Capital Transit; railway:traction=electric
A17: L16 | B17: Benning Road – Kenilworth branch | C17: Benning Rd NE east from 15th & H NE across the Anacostia to Kenilworth | D17: DC | E17: Columbia Railway | F17: WRECo; Capital Transit | G17: Electric | H17: 1898 | I17: — | J17: — | K17: 1898 | L17: 10 | M17: May 1, 1949 | N17: 1949 | O17: Bus V8 / X2 | P17: Benning Rd car barn built 1941. 1912 map (audit): the branch left Benning Rd just west of Minnesota Ave and ran northeast on its own alignment to Kenilworth; redrawn. | Q17: WP; CRF; MPD | R17: 6.23 | S17: 4.98 | T17: L17, V08 | U17: type=chronology name=Benning Road – Kenilworth branch network=Washington, D.C. streetcars operator=Columbia Railway start_date=1898 end_date=1949 ref:streetcar_project=L16 ref=10 description=Later operators: WRECo; Capital Transit source=WP; CRF; MPD Dated route relations in this chronology: 1898–1902: 6 ways; operator=Columbia Railway; railway:traction=electric 1902–1934: 6 ways; operator=Washington Railway & Electric; railway:traction=electric 1934–1949: 6 ways; operator=Capital Transit; railway:traction=electric
A18: L17 | B18: Seat Pleasant branch | C18: Benning Rd to Deanwood Junction and Seat Pleasant, MD (connection with the Chesapeake Beach Railway) | D18: DC/MD | E18: Columbia Railway | F18: WRECo; Capital Transit | G18: Electric | H18: 1900 | I18: — | J18: — | K18: 1898/1900 | L18: 12 (Seat Pleasant) | M18: May 1, 1949 (Wikipedia: Kenilworth–Seat Pleasant bus substitution 1948) | N18: 1949 | O18: Bus U8 | P18: Seat Pleasant loop built 1945. 1912 map: ran from Benning Rd up Minnesota Ave and east along Deane Ave (today's Nannie Helen Burroughs Ave) and Dix St to the District line, matching Berman's 1942 map. 1912 map (audit): shared the Kenilworth branch alignment from Benning Rd, then ran straight along Deane Ave (Nannie Helen Burroughs Ave) to the District line; redrawn. | Q18: WP; MPD; CRF | R18: 4.64 | S18: 1.56 | T18: L16, V08 | U18: type=chronology name=Seat Pleasant branch network=Washington, D.C. streetcars operator=Columbia Railway start_date=1900 end_date=1949 ref:streetcar_project=L17 ref=12 description=Later operators: WRECo; Capital Transit source=WP; MPD; CRF Dated route relations in this chronology: 1900–1902: 4 ways; operator=Columbia Railway; railway:traction=electric 1902–1934: 4 ways; operator=Washington Railway & Electric; railway:traction=electric 1934–1949: 4 ways; operator=Capital Transit; railway:traction=electric
A19: L18 | B19: Anacostia & Potomac River Railroad main line | C19: Along M St from the Maine Ave/M St waterfront to 11th St SE, across the Navy Yard Bridge to Uniontown (Nichols Ave & V St SE), as mapped in 1880. 1888: extensions toward Congressional Cemetery and Center Market; Nichols Ave toward St. Elizabeths (Government Hospital for the Insane) | D19: DC | E19: Anacostia & Potomac River Railroad | F19: WRECo (controlling stock 1912); Capital Transit | G19: Horse → electric (April 1900, the last horse line in DC) | H19: 1875 | I19: 1875 | J19: — | K19: 1900 | L19: — (Anacostia service later part of routes 54/A2 corridor) | M19: Between 1924 and 1942 (still drawn on the 1924 Rand McNally map; nothing crosses the Anacostia on the 1942 map) | O19: — | P19: First line to cross the Anacostia River. Probably ended with the 1935 Anacostia conversions, but no source confirms it. Map: the 1888 Center Market branch (G St, 4th St, E St and Canal St SE) is drawn on the 1912 map. 1912 map: the line ran up 11th St SE to G St; there is no track on M St SE, on 7th St SE, or on G St east of 11th St, so those sections are drawn only to 1900 (estimated). 1912 map: the Center Market branch ran up Canal St, west on Maryland Ave, north on 4½ St and along Missouri Ave and B St to 7th St. 1912 map: M St SW between the waterfront and 4½ St was still in use. | Q19: WP; MPD; MAP1880; MAP1910; MAP1924; MAP1942 | R19: 12.53 | S19: 2.89 | T19: L01, L02, L08, L22 | U19: type=chronology name=Anacostia & Potomac River Railroad main line network=Washington, D.C. streetcars operator=Anacostia & Potomac River Railroad start_date=1875 end_date=1935 ref:streetcar_project=L18 end_date:edtf=1935~ ref=54 description=Later operators: WRECo (controlling stock 1912); Capital Transit source=WP; MPD; MAP1880; MAP1910; MAP1924; MAP1942 Dated route relations in this chronology: 1875–1888: 7 ways; operator=Anacostia & Potomac River Railroad; railway:traction=horse 1888–1900: 21 ways; operator=Anacostia & Potomac River Railroad; railway:traction=horse 1900–1912: 16 ways; operator=Anacostia & Potomac River Railroad; railway:traction=electric 1912–1934: 16 ways; operator=Washington Railway & Electric; railway:traction=electric 1934–1935: 16 ways; operator=Capital Transit; railway:traction=electric
A20: L19 | B20: 11th Street line | C20: 11th St: north to Boundary St and south to Water St SW (Belt, 1881); A&PR extended it from F St NW to Florida Ave (1898) and by double track north on 11th St to Lydecker Ave (1902); later to 11th & Monroe NW and through-routed to Anacostia | D20: DC | E20: Belt Railway (11th St line, 1881); extended by the A&PR (1898) | F20: Washington Traction & Electric; WRECo; Capital Transit; D.C. Transit | G20: Horse → electric (1900) | H20: 1875 | I20: 1875 | J20: — | K20: 1900 | L20: 60 (11th & Monroe); 62; 64 | M20: Dec 3, 1961 | N20: 1961 | O20: Bus 66 | Q20: MPD; CRF; GDC; LAWS | R20: 4.03 | S20: 1.49 | T20: L22 | U20: type=chronology name=11th Street line network=Washington, D.C. streetcars operator=Belt Railway (11th St line, 1881); extended by the A&PR (1898) start_date=1875 end_date=1961 ref:streetcar_project=L19 ref=60;62;64 description=Later operators: Washington Traction & Electric; WRECo; Capital Transit; D.C. Transit source=MPD; CRF; GDC; LAWS Dated route relations in this chronology: 1875–1900: 8 ways; operator=Belt Railway; railway:traction=horse 1900–1902: 8 ways; operator=Belt Railway; railway:traction=electric 1902–1912: 10 ways; operator=Belt Railway; railway:traction=electric 1912–1934: 10 ways; operator=Washington Railway & Electric; railway:traction=electric 1934–1956: 10 ways; operator=Capital Transit; railway:traction=electric 1956–1961: 10 ways; operator=D.C. Transit; railway:traction=electric
A21: L20 | B21: Capital Railway – Anacostia–Congress Heights | C21: Navy Yard Bridge – Nichols Ave SE to Congress Heights (Upsal St by 1898); later extended past Alabama Ave to Sterling St SE | D21: DC | E21: Capital Railway (chartered Mar 2, 1895) | F21: A&PR (1899); WRECo; Capital Transit | G21: Brown magnetic surface contact (1897, failed) and double-overhead on the bridge → electric | H21: 1896 | I21: — | J21: — | K21: 1896 | L21: — (bus A2) | M21: June 16, 1935 (CRF) / last car July 16, 1935 (Wikipedia) | N21: 1935 | O21: Bus A2 | P21: Anacostia's first electric line. | Q21: WP; MPD; CRF | R21: 1.73 | S21: 0.68 | T21: L21 | U21: type=chronology name=Capital Railway – Anacostia–Congress Heights network=Washington, D.C. streetcars operator=Capital Railway (chartered Mar 2, 1895) start_date=1896 end_date=1935 ref:streetcar_project=L20 description=Later operators: A&PR (1899); WRECo; Capital Transit source=WP; MPD; CRF Dated route relations in this chronology: 1896–1912: 10 ways; operator=Capital Railway; railway:traction=electric 1912–1934: 10 ways; operator=Washington Railway & Electric; railway:traction=electric 1934–1935: 10 ways; operator=Capital Transit; railway:traction=electric
A22: L21 | B22: Portland Street / Firth Sterling spur | C22: Nichols Ave along Portland St to the Firth Sterling Steel works (now part of Joint Base Anacostia-Bolling) | D22: DC | E22: WRECo | F22: — | G22: Electric (single track, doubled 1916) | H22: 1912 | I22: — | J22: — | K22: 1912 | L22: — | M22: Service suspended by 1923 | N22: 1923 | O22: — | P22: About one mile of track. | Q22: MPD | R22: 1.41 | S22: 0.68 | T22: L20 | U22: type=chronology name=Portland Street / Firth Sterling spur network=Washington, D.C. streetcars operator=WRECo start_date=1912 end_date=1923 ref:streetcar_project=L21 source=MPD Dated route relations in this chronology: 1912–1923: 10 ways; operator=Washington Railway & Electric; railway:traction=electric
A23: L22 | B23: Belt Railway loop | C23: Capitol – 1st St SW – Maryland & Virginia Aves SW – 12th St – Ohio Ave – 14th St – O St NW (10 blocks east) – 4th St – G St – 1st St NW; P St NW westbound track (1876) | D23: DC | E23: Capitol, North O Street & South Washington Railway (renamed Belt Railway 1893) | F23: Anacostia & Potomac River (1898); WRECo | G23: Horse → compressed-air trial (1896) → electric conduit (1899) | H23: 1875 | I23: 1875 | J23: — | K23: 1899 | L23: — | M23: Absorbed into other routes; end date not stated | O23: — | P23: 8.5 miles of track. Car barn at 3rd & B (Independence) Sts SW. 1912 map: the loop's south side ran along Maryland Ave SW from 12th St to the Capitol grounds. 1912 map: a branch ran down 11th St SW to the waterfront and along Water St to 7th St. 1912 map (audit): south of New York Ave the loop used New York Ave and 5th St to reach G St, not 4th St. | Q23: WP; MPD | R23: 11.36 | S23: 4.99 | T23: L01, L02, L04, L18, L19, L33, L48, L51, L55, L58, V01 | U23: type=chronology name=Belt Railway loop network=Washington, D.C. streetcars operator=Capitol, North O Street & South Washington Railway (renamed Belt Railway 1893) start_date=1875 end_date=1933 ref:streetcar_project=L22 end_date:edtf=1933~ description=Later operators: Anacostia & Potomac River (1898); WRECo source=WP; MPD Dated route relations in this chronology: 1875–1876: 40 ways; operator=Capitol, North O Street & South Washington Railway; railway:traction=horse 1876–1899: 44 ways; operator=Capitol, North O Street & South Washington Railway; railway:traction=horse 1899–1912: 44 ways; operator=Capitol, North O Street & South Washington Railway; railway:traction=electric 1912–1933: 44 ways; operator=Washington Railway & Electric; railway:traction=electric
A24: L23 | B24: Eckington & Soldiers' Home Railway | C24: Charter: New York Ave from 7th St to 3rd St NE, 3rd St to T St, T St to 4th St, 4th St to Bunker Hill Rd (Michigan Ave). As built: 7th & New York Ave via Boundary St, Eckington Pl, R St, 3rd St and T St NE to the car barn at 4th & T NE | D24: DC | E24: Eckington & Soldiers' Home Railway | F24: City & Suburban (1898); WRECo; Capital Transit | G24: DC's first electric line (overhead, Oct 17, 1888) → batteries (1891–93) → horses → compressed air (1896) → conduit (1899) | H24: 1888 | I24: — | J24: — | K24: 1888 | L24: — | M24: Not stated for the trunk | O24: — | P24: 2.5 miles. Also tried the Wheless and Willis magnetic surface-contact systems on North Capitol St. 1912 map: the Eckington loop used both 2nd and 3rd Sts NE between R and T Sts. | Q24: WP; MPD | R24: 3.11 | S24: 0.14 | T24: L25 | U24: type=chronology name=Eckington & Soldiers' Home Railway network=Washington, D.C. streetcars operator=Eckington & Soldiers' Home Railway start_date=1888 end_date=1958 ref:streetcar_project=L23 end_date:edtf=1958~ description=Later operators: City & Suburban (1898); WRECo; Capital Transit source=WP; MPD Dated route relations in this chronology: 1888–1902: 10 ways; operator=Eckington & Soldiers' Home Railway; railway:traction=electric 1902–1934: 10 ways; operator=Washington Railway & Electric; railway:traction=electric 1934–1956: 10 ways; operator=Capital Transit; railway:traction=electric 1956–1958: 10 ways; operator=D.C. Transit; railway:traction=electric
A25: L24 | B25: NE 4th Street branch | C25: 4th St NE north to Michigan Ave; later a Michigan Ave extension to the B&O Metropolitan Branch | D25: DC | E25: Eckington & Soldiers' Home Railway | F25: WRECo | G25: Electric | H25: 1888 | I25: — | J25: — | K25: 1888 | L25: — (bus F4/G8) | M25: 1920s | N25: 1925 | O25: Bus G8 | P25: CRF gives '1920s' only; end year approximate. | Q25: WP; CRF | R25: 1.74 | S25: 0 | T25: — | U25: type=chronology name=NE 4th Street branch network=Washington, D.C. streetcars operator=Eckington & Soldiers' Home Railway start_date=1888 end_date=1925 ref:streetcar_project=L24 description=Later operators: WRECo source=WP; CRF Dated route relations in this chronology: 1888–1902: 2 ways; operator=Eckington & Soldiers' Home Railway; railway:traction=electric 1902–1925: 2 ways; operator=Washington Railway & Electric; railway:traction=electric
A26: L25 | B26: Glenwood Cemetery extension | C26: T St, 2nd St and V St NE to Glenwood Cemetery | D26: DC | E26: Eckington & Soldiers' Home Railway | F26: — | G26: Electric | H26: 1889 | I26: — | J26: — | K26: 1889 | L26: — | M26: 1894 (unprofitable) | N26: 1894 | O26: — | Q26: WP; MPD | R26: 1.62 | S26: 1.05 | T26: L23, L26 | U26: type=chronology name=Glenwood Cemetery extension network=Washington, D.C. streetcars operator=Eckington & Soldiers' Home Railway start_date=1889 end_date=1894 ref:streetcar_project=L25 source=WP; MPD Dated route relations in this chronology: 1889–1894: 6 ways; operator=Eckington & Soldiers' Home Railway; railway:traction=electric
A27: L26 | B27: North Capitol Street / Brookland line | C27: North Capitol St to the Soldiers' Home; extended to Brookland (Catholic University) 1899–1900; Brookland/Quincy St loop 1948 | D27: DC | E27: Eckington & Soldiers' Home Railway | F27: WRECo; Capital Transit; D.C. Transit | G27: Electric (1890 per CRF) | H27: 1890 | I27: — | J27: — | K27: 1890 | L27: 80 | M27: Sept 7, 1958 (CRF) / 1959 (Wikipedia) | N27: 1958 | O27: Bus 80 | P27: 1912 map: continued north on 12th St NE past Monroe St to about Randolph St. | Q27: WP; MPD; CRF; GDC | R27: 5.97 | S27: 1.12 | T27: L25, L33 | U27: type=chronology name=North Capitol Street / Brookland line network=Washington, D.C. streetcars operator=Eckington & Soldiers' Home Railway start_date=1890 end_date=1958 ref:streetcar_project=L26 ref=80 description=Later operators: WRECo; Capital Transit; D.C. Transit source=WP; MPD; CRF; GDC Dated route relations in this chronology: 1890–1899: 10 ways; operator=Eckington & Soldiers' Home Railway; railway:traction=electric 1899–1902: 12 ways; operator=Eckington & Soldiers' Home Railway; railway:traction=electric 1902–1934: 12 ways; operator=Washington Railway & Electric; railway:traction=electric 1934–1956: 12 ways; operator=Capital Transit; railway:traction=electric 1956–1958: 12 ways; operator=D.C. Transit; railway:traction=electric
A28: L27 | B28: G Street extension | C28: 5th St from New York Ave to G St, then G St NW to 15th St (c.1890); 1892–94 downtown loops via 1st St, C St and D St NW, New Jersey Ave, and 5th St, Louisiana Ave, 6th St and B St NW to near 7th St (Center Market) | D28: DC | E28: Eckington & Soldiers' Home Railway | F28: WRECo | G28: Battery trials (1891–93), then electric | H28: 1891 | I28: — | J28: — | K28: 1891 | L28: — | M28: Not stated | O28: — | P28: Authorized 1890. | Q28: MPD; LAWS | R28: 1.91 | S28: 0 | T28: — | U28: type=chronology name=G Street extension network=Washington, D.C. streetcars operator=Eckington & Soldiers' Home Railway start_date=1891 end_date=1958 ref:streetcar_project=L27 end_date:edtf=1958~ description=Later operators: WRECo source=MPD; LAWS Dated route relations in this chronology: 1891–1902: 11 ways; operator=Eckington & Soldiers' Home Railway; railway:traction=electric 1902–1934: 11 ways; operator=Washington Railway & Electric; railway:traction=electric 1934–1956: 11 ways; operator=Capital Transit; railway:traction=electric 1956–1958: 11 ways; operator=D.C. Transit; railway:traction=electric
A29: L28 | B29: Rhode Island Avenue – College Park line | C29: Rhode Island Ave NE from 4th St NE (connection with Eckington line) to Mount Rainier (1897), Brentwood (1898), Hyattsville and Riverdale (1899), then College Park and Berwyn | D29: DC/MD | E29: Maryland & Washington Railway / City & Suburban Railway | F29: WRECo (fully 1926); Capital Transit; D.C. Transit | G29: Electric | H29: 1897 | I29: — | J29: — | K29: 1897 | L29: 82 (College Park); P6 bus later | M29: Sept 7, 1958 (Route 82, one of the first abandoned by D.C. Transit) | N29: 1958 | O29: Bus 82 / P6 | P29: Truncated at Beltsville by 1948 and at Berwyn by 1956. Right-of-way partly used by the Rhode Island Ave Trolley Trail. | Q29: WPMD; MPD; CRF | R29: 11.96 | S29: 0.24 | T29: L29 | U29: type=chronology name=Rhode Island Avenue – College Park line network=Washington, D.C. streetcars operator=Maryland & Washington Railway / City & Suburban Railway start_date=1897 end_date=1958 ref:streetcar_project=L28 ref=82 description=Later operators: WRECo (fully 1926); Capital Transit; D.C. Transit source=WPMD; MPD; CRF Dated route relations in this chronology: 1897–1899: 1 ways; operator=Maryland & Washington Railway / City & Suburban Railway; railway:traction=electric 1899–1900: 2 ways; operator=Maryland & Washington Railway / City & Suburban Railway; railway:traction=electric 1900–1902: 4 ways; operator=Maryland & Washington Railway / City & Suburban Railway; railway:traction=electric 1902–1934: 4 ways; operator=Washington Railway & Electric; railway:traction=electric 1934–1956: 4 ways; operator=Capital Transit; railway:traction=electric 1956–1958: 4 ways; operator=D.C. Transit; railway:traction=electric
A30: L29 | B30: Berwyn – Beltsville – Laurel extension | C30: Riverdale–College Park–Berwyn–Branchville–Beltsville–Contee–Laurel, MD | D30: MD | E30: Columbia & Maryland Ry / Berwyn & Laurel Electric RR / Washington, Berwyn & Laurel Electric RR | F30: City & Suburban; WRECo (1910); Capital Transit | G30: Electric | H30: 1902 | I30: — | J30: — | K30: 1902 | L30: 84 (Branchville–Beltsville) | M30: Branchville–Beltsville: July 31, 1949 (CRF); Laurel end not stated | N30: 1949 | O30: Discontinued | P30: Direct Treasury–Laurel service began 1902. | Q30: WPMD; MPD; CRF | R30: 13.68 | S30: 0.24 | T30: L28 | U30: type=chronology name=Berwyn – Beltsville – Laurel extension network=Washington, D.C. streetcars operator=Columbia & Maryland Ry / Berwyn & Laurel Electric RR / Washington, Berwyn & Laurel Electric RR start_date=1902 end_date=1949 ref:streetcar_project=L29 ref=84 description=Later operators: City & Suburban; WRECo (1910); Capital Transit source=WPMD; MPD; CRF Dated route relations in this chronology: 1902–1934: 4 ways; operator=Washington Railway & Electric; railway:traction=electric 1934–1948: 4 ways; operator=Capital Transit; railway:traction=electric 1948–1949: 3 ways; operator=Capital Transit; railway:traction=electric
A31: L30 | B31: Rock Creek Railway – Connecticut Avenue line | C31: Florida Ave (2 blocks east of Connecticut) – 18th St – Calvert St bridge (1891) – Connecticut Ave to Chevy Chase Circle and Chevy Chase Lake, MD | D31: DC/MD | E31: Rock Creek Railway | F31: Capital Traction (1895); Capital Transit | G31: Overhead outside the city; Love conduit inside (1893–99) | H31: 1890 | I31: — | J31: — | K31: 1892 | L31: — (buses L2/L6) | M31: Sept 16, 1935 (Calvert St bridge to Chevy Chase Lake) | N31: 1935 | O31: Bus L2 / L6 | P31: Florida Ave stub (Connecticut Ave–18th St) opened 1890 and was removed 1899. Calvert St bridge completed July 21, 1891. Suburban line opened Sept 16 (Wikipedia) or 18 (NRHP), 1892. Through service to Kensington from 1923. Last cars Sept 15, 1935. | Q31: WP; MPD; CRF | R31: 10.18 | S31: 0 | T31: — | U31: type=chronology name=Rock Creek Railway – Connecticut Avenue line network=Washington, D.C. streetcars operator=Rock Creek Railway start_date=1890 end_date=1935 ref:streetcar_project=L30 description=Later operators: Capital Traction (1895); Capital Transit source=WP; MPD; CRF Dated route relations in this chronology: 1890–1892: 1 ways; operator=Rock Creek Railway; railway:traction=horse 1892–1895: 4 ways; operator=Rock Creek Railway; railway:traction=electric 1895–1899: 4 ways; operator=Capital Traction; railway:traction=electric 1899–1934: 3 ways; operator=Capital Traction; railway:traction=electric 1934–1935: 3 ways; operator=Capital Transit; railway:traction=electric
A32: L31 | B32: U Street line | C32: U St east from 18th St to 7th St NW (1893, Love conduit), later the U St crosstown | D32: DC | E32: Rock Creek Railway | F32: Capital Traction; Capital Transit; D.C. Transit | G32: Electric (Love conduit 1893, standard conduit 1899) | H32: 1893 | I32: — | J32: — | K32: 1892/1893 | L32: 90, 92 (U St crosstown) | M32: Jan 28, 1962 | N32: 1962 | O32: Bus 90/92 | P32: Opened Mar 2, 1893 (18th & Florida to 7th St). Love conduit replaced by sliding shoe in 1899. In 1946, routes 90/92 started at the National Zoological Park via Calvert St (Tundria lists 16th St where other sources say 18th St). | Q32: WP; MPD; CRF; GGW; TUN | R32: 1.86 | S32: 0.09 | T32: L06 | U32: type=chronology name=U Street line network=Washington, D.C. streetcars operator=Rock Creek Railway start_date=1893 end_date=1962 ref:streetcar_project=L31 ref=90;92 description=Later operators: Capital Traction; Capital Transit; D.C. Transit source=WP; MPD; CRF; GGW; TUN Dated route relations in this chronology: 1893–1895: 6 ways; operator=Rock Creek Railway; railway:traction=electric 1895–1934: 6 ways; operator=Capital Traction; railway:traction=electric 1934–1956: 6 ways; operator=Capital Transit; railway:traction=electric 1956–1962: 6 ways; operator=D.C. Transit; railway:traction=electric
A33: L32 | B33: Florida Avenue / 8th Street extension | C33: U St line extended east on Florida Ave NW/NE to 8th St NE, then south on 8th St NE/SE to the Navy Yard | D33: DC | E33: Capital Traction (Act of May 23, 1908; per Tindall and Wikipedia's Capital Traction article; Wikipedia's main article says WRECo) | F33: Capital Transit; D.C. Transit | G33: Electric | H33: 1908 | I33: — | J33: — | K33: 1908 | L33: 90, 92 | M33: Jan 28, 1962 | N33: 1962 | O33: Bus 90/92 | P33: Rails still buried under 8th St SE. Drawn on the 1910 and 1924 Rand McNally maps. 1912 map: Capital Traction track on F St NE linked Union Station with the 8th St line. | Q33: WP; CRF | R33: 6.51 | S33: 0.89 | T33: L01, L48 | U33: type=chronology name=Florida Avenue / 8th Street extension network=Washington, D.C. streetcars operator=Capital Traction (Act of May 23, 1908; per Tindall and Wikipedia's Capital Traction article; Wikipedia's main article says WRECo) start_date=1908 end_date=1962 ref:streetcar_project=L32 ref=90;92 description=Later operators: Capital Transit; D.C. Transit source=WP; CRF Dated route relations in this chronology: 1908–1934: 15 ways; operator=Capital Traction; railway:traction=electric 1934–1956: 15 ways; operator=Capital Transit; railway:traction=electric 1956–1962: 15 ways; operator=D.C. Transit; railway:traction=electric
A34: L33 | B34: New Jersey Avenue line | C34: Florida Ave & New Jersey Ave via New Jersey Ave and Massachusetts Ave to the Union Station plaza (Act of May 23, 1908) | D34: DC | E34: Capital Traction | F34: Capital Transit; D.C. Transit | G34: Electric | H34: 1908 | I34: — | J34: — | K34: 1908 | L34: 90 (old route) | M34: Jan 28, 1962 | N34: 1962 | O34: — | Q34: CRF | R34: 2.31 | S34: 0.35 | T34: L22, L26, L48, L55 | U34: type=chronology name=New Jersey Avenue line network=Washington, D.C. streetcars operator=Capital Traction start_date=1908 end_date=1962 ref:streetcar_project=L33 ref=90 description=Later operators: Capital Transit; D.C. Transit source=CRF Dated route relations in this chronology: 1908–1934: 9 ways; operator=Capital Traction; railway:traction=electric 1934–1956: 9 ways; operator=Capital Transit; railway:traction=electric 1956–1962: 9 ways; operator=D.C. Transit; railway:traction=electric
A35: L34 | B35: Union Station trackage | C35: Delaware Ave NE and Massachusetts Ave NE to Union Station; C St tunnel under Capitol Plaza (1934) | D35: DC | E35: Capital Traction & WRECo | F35: Capital Transit; D.C. Transit | G35: Electric | H35: 1908 | I35: — | J35: — | K35: 1908 | L35: 90, 92 | M35: Jan 1962 | N35: 1962 | O35: — | P35: Service began June 24, 1908 (Wikipedia Capital Traction article) or Dec 6, 1908 (NRHP). Capitol Plaza tunnel opened 1934. Map: joint track ran south from Union Station on 1st St NE/SE to Pennsylvania Ave SE (1912 map; route 90 in 1946). | Q35: WP; MPD | R35: 1.71 | S35: 0.67 | T35: L01, L02, L09, L55 | U35: type=chronology name=Union Station trackage network=Washington, D.C. streetcars operator=Capital Traction & WRECo start_date=1908 end_date=1962 ref:streetcar_project=L34 ref=90;92 description=Later operators: Capital Transit; D.C. Transit source=WP; MPD Dated route relations in this chronology: 1908–1934: 8 ways; operator=Capital Traction; railway:traction=electric 1934–1956: 8 ways; operator=Capital Transit; railway:traction=electric 1956–1962: 8 ways; operator=D.C. Transit; railway:traction=electric
A36: L35 | B36: Kensington Railway | C36: Chevy Chase Lake north along Connecticut Ave to University Blvd, Kensington; extended 1.5 miles north by 1916 | D36: MD | E36: Chevy Chase Lake & Kensington Railway (1894) | F36: Kensington Railway; leased to Capital Traction 1923–33 | G36: Electric (single track) | H36: 1895 | I36: — | J36: — | K36: 1895 | L36: — | M36: Sept 15, 1935 | N36: 1935 | O36: — | P36: Opened May 30, 1895. Right-of-way became Kensington Parkway. | Q36: WPMD | R36: 3.76 | S36: 0 | T36: — | U36: type=chronology name=Kensington Railway network=Washington, D.C. streetcars operator=Chevy Chase Lake & Kensington Railway (1894) start_date=1895 end_date=1935 ref:streetcar_project=L35 description=Later operators: Kensington Railway; leased to Capital Traction 1923–33 source=WPMD Dated route relations in this chronology: 1895–1935: 1 ways; operator=Chevy Chase Lake & Kensington Railway; railway:traction=electric
A37: L36 | B37: Georgetown & Tennallytown line | C37: M St NW up 32nd St and Wisconsin Ave (Georgetown & Rockville Rd) to Tenleytown and Friendship Heights | D37: DC | E37: Georgetown & Tennallytown Railway | F37: Washington Traction & Electric; WRECo (fully 1926); Capital Transit; D.C. Transit | G37: Overhead electric (1890) | H37: 1890 | I37: — | J37: — | K37: 1890 | L37: 30, 31 (Wisconsin Ave) | M37: Jan 3, 1960 | N37: 1960 | O37: Bus 30s | P37: Opened Apr 25, 1890. | Q37: WP; MPD; CRF | R37: 6.58 | S37: 0.3 | T37: L01, L07 | U37: type=chronology name=Georgetown & Tennallytown line network=Washington, D.C. streetcars operator=Georgetown & Tennallytown Railway start_date=1890 end_date=1960 ref:streetcar_project=L36 ref=30;31 description=Later operators: Washington Traction & Electric; WRECo (fully 1926); Capital Transit; D.C. Transit source=WP; MPD; CRF Dated route relations in this chronology: 1890–1902: 7 ways; operator=Georgetown & Tennallytown Railway; railway:traction=electric 1902–1934: 7 ways; operator=Washington Railway & Electric; railway:traction=electric 1934–1956: 7 ways; operator=Capital Transit; railway:traction=electric 1956–1960: 7 ways; operator=D.C. Transit; railway:traction=electric
A38: L37 | B38: Friendship Heights – Bethesda – Rockville line | C38: Wisconsin & Willard Aves along Old Georgetown Rd to Bethesda (Bethesda Park, 3.75 mi); extended to Rockville | D38: MD | E38: Tennallytown & Rockville RR (1890); Washington & Rockville Railway (1897) | F38: WRECo; Capital Transit | G38: Electric | H38: 1890 | I38: — | J38: — | K38: 1890 | L38: — (bus T6) | M38: Aug 4, 1935 | N38: 1935 | O38: Bus T6 (later Ride-On) | P38: T&R opened July 4, 1891 to Bethesda Park; foreclosed May 1896. W&R incorporated Sept 9, 1897; tracks to Rockville by 1900, Woodlawn Hotel 1904. 24 trips a day in 1929. | Q38: WP; MPD; CRF | R38: 15.49 | S38: 0 | T38: — | U38: type=chronology name=Friendship Heights – Bethesda – Rockville line network=Washington, D.C. streetcars operator=Tennallytown & Rockville RR (1890); Washington & Rockville Railway (1897) start_date=1890 end_date=1935 ref:streetcar_project=L37 description=Later operators: WRECo; Capital Transit source=WP; MPD; CRF Dated route relations in this chronology: 1891–1900: 3 ways; operator=Tennallytown & Rockville RR; railway:traction=electric 1900–1902: 4 ways; operator=Tennallytown & Rockville RR; railway:traction=electric 1902–1934: 4 ways; operator=Washington Railway & Electric; railway:traction=electric 1934–1935: 4 ways; operator=Capital Transit; railway:traction=electric
A39: L38 | B39: Glen Echo Railroad | C39: Wisconsin & Willard Aves west to Conduit Rd (MacArthur Blvd) & Walhonding Rd; extended 1896 to Glen Echo and Cabin John | D39: MD | E39: Glen Echo Railroad (1889); Washington & Glen Echo RR (1896) | F39: Walhonding–Cabin John section absorbed by Washington & Great Falls (1902) | G39: Electric | H39: 1891 | I39: — | J39: — | K39: 1891 | L39: — | M39: Oct 1902 | N39: 1902 | O39: — | P39: Opened June 1891. | Q39: WPMD; MPD | R39: 6.39 | S39: 0.4 | T39: L39 | U39: type=chronology name=Glen Echo Railroad network=Washington, D.C. streetcars operator=Glen Echo Railroad (1889); Washington & Glen Echo RR (1896) start_date=1891 end_date=1902 ref:streetcar_project=L38 description=Later operators: Walhonding–Cabin John section absorbed by Washington & Great Falls (1902) source=WPMD; MPD Dated route relations in this chronology: 1891–1896: 1 ways; operator=Glen Echo Railroad; railway:traction=electric 1896–1902: 9 ways; operator=Glen Echo Railroad; railway:traction=electric
A40: L39 | B40: Cabin John line (Washington & Great Falls) | C40: Falls car barn at 36th & Prospect Sts, west along Prospect St and across the Foundry Branch trestle, then on its own right-of-way along the south side of the Georgetown Reservoir and through the Palisades (today's Palisades Trolley Trail), past Chain Bridge and north through Brookmont to Glen Echo Park, then on the old Glen Echo Railroad right-of-way to a turning loop at the east end of the Cabin John Bridge | D40: DC/MD | E40: Washington & Great Falls Electric Railway | F40: WRECo (1902); Capital Transit; D.C. Transit | G40: Electric | H40: 1895 | I40: — | J40: — | K40: 1895 | L40: 20 (Cabin John); 22 (Washington Circle) | M40: Jan 3, 1960 | N40: 1960 | O40: Buses (later Ride-On) | P40: Chartered July 29, 1892. Reached the MD line Sept 28, 1895 and Cabin John 1897; double-tracked by 1899. Foundry Branch trestle survives. Route checked against the 1897 company map, the 1907 Baist atlas and the 1951 USGS topographic map: the line ran through Brookmont (not along MacArthur Blvd past the Dalecarlia plant) and ended at a loop by the Cabin John Bridge, not in Cabin John village. Alignment traced from OpenStreetMap's mapped trolley right-of-way, the Foundry Branch trestle and the Cabin John loop. 1912 map: from the car barn the line ran west along the bluff below Georgetown University and curved north to the Foundry Branch trestle. | Q40: WP; WPMD; MPD; CRF; DDOT Palisades Trolley Trail Historic Resources Report (2019); USGS 1951 topo | R40: 12.46 | S40: 1.95 | T40: L07, L38, V07 | U40: type=chronology name=Cabin John line (Washington & Great Falls) network=Washington, D.C. streetcars operator=Washington & Great Falls Electric Railway start_date=1895 end_date=1960 ref:streetcar_project=L39 ref=20;22 description=Later operators: WRECo (1902); Capital Transit; D.C. Transit source=WP; WPMD; MPD; CRF; DDOT Palisades Trolley Trail Historic Resources Report (2019); USGS 1951 topo Dated route relations in this chronology: 1895–1897: 1 ways; operator=Washington & Great Falls Electric Railway; railway:traction=electric 1897–1902: 11 ways; operator=Washington & Great Falls Electric Railway; railway:traction=electric 1902–1934: 11 ways; operator=Washington Railway & Electric; railway:traction=electric 1934–1935: 11 ways; operator=Capital Transit; railway:traction=electric 1935–1956: 18 ways; operator=Capital Transit; railway:traction=electric 1956–1960: 18 ways; operator=D.C. Transit; railway:traction=electric
A41: L52 | B41: West Washington & Great Falls Electric Railway | C41: Junction with the Tennallytown & Rockville at Wisconsin Ave, west to Glen Echo, largely along today's Bradley Blvd | D41: MD | E41: West Washington & Great Falls Electric Railway | F41: Washington & Great Falls (July 1, 1896); WRECo | G41: Electric | H41: 1896 | I41: — | J41: — | K41: 1896 | L41: — | M41: Not stated | O41: — | P41: Founded Nov 1, 1895. May overlap with the Glen Echo RR's Chevy Chase branch. | Q41: WP-WRECo; TIN | T41: Not drawn
A42: L53 | B42: Brightwood Ry – Petworth / Kenyon St branch | C42: Rock Creek Church Rd & Richmond St (Petworth) west on Richmond St to Georgia Ave; south on Georgia Ave to Marshall St; west on Marshall St to Kenyon Ave; Kenyon to 14th St | D42: DC | E42: Brightwood Railway | F42: — | G42: Overhead trolley | H42: 1893 | I42: — | J42: — | K42: 1893 | L42: — | M42: Ordered vacated between 7th and 14th Sts (act c.1893–95) | N42: 1895 | O42: — | P42: Authorized Feb 27, 1893. A later act ordered the Kenyon and Marshall St track and poles removed within a month unless converted to underground power. End year approximate. | Q42: LAWS | R42: 0.83 | S42: 0 | T42: — | U42: type=chronology name=Brightwood Ry – Petworth / Kenyon St branch network=Washington, D.C. streetcars operator=Brightwood Railway start_date=1893 end_date=1895 ref:streetcar_project=L53 source=LAWS Dated route relations in this chronology: 1893–1895: 2 ways; operator=Brightwood Railway; railway:traction=electric
A43: L55 | B43: City & Suburban – Stanton Square / C & D St NE loop | C43: From New Jersey Ave east on C St around Stanton Square, then C and D Sts NE to a turn at 13th St; Stanton Square track moved to the north side c.1902–03 | D43: DC | E43: Eckington & Soldiers' Home Railway | F43: City & Suburban; WRECo | G43: Electric | H43: 1894 | I43: — | J43: — | K43: 1894 | L43: 42 (to 13th & C/D NE) | M43: Dec 3, 1961 (with route 42) | N43: 1961 | O43: Bus 42 | P43: Authorized 1892, route rewritten Aug 23, 1894. Drawn on the 1910 and 1924 Rand McNally maps and on the 1942 and 1958 system maps. In 1946, route 42 ran out via Massachusetts Ave, Maryland Ave and D St to 13th St, returning via C and 6th Sts (Tundria). The 1912 map colors this loop as WRECo. 1912 map: track on Massachusetts Ave NE linked Union Station with Stanton Square (route 42 used it in 1946). 1912 map: cars reached Stanton Square from Union Station by Massachusetts Ave, ran along the square's north side and down 6th St to C St; C St west of the square is not shown in 1912, so it is drawn only to 1908 (estimated). | Q43: LAWS; MAP1910; MAP1924; MAP1942; MAP1958; TUN; MAP1912 | R43: 5.45 | S43: 1.12 | T43: L04, L09, L22, L33, L34 | U43: type=chronology name=City & Suburban – Stanton Square / C & D St NE loop network=Washington, D.C. streetcars operator=Eckington & Soldiers' Home Railway start_date=1894 end_date=1961 ref:streetcar_project=L55 ref=42 description=Later operators: City & Suburban; WRECo source=LAWS; MAP1910; MAP1924; MAP1942; MAP1958; TUN; MAP1912 Dated route relations in this chronology: 1894–1902: 15 ways; operator=Eckington & Soldiers' Home Railway; railway:traction=electric 1902–1908: 15 ways; operator=Washington Railway & Electric; railway:traction=electric 1908–1934: 7 ways; operator=Washington Railway & Electric; railway:traction=electric 1934–1956: 7 ways; operator=Capital Transit; railway:traction=electric 1956–1961: 7 ways; operator=D.C. Transit; railway:traction=electric
A44: L56 | B44: West End loops / Potomac Park terminal | C44: First loops (1901): out Pennsylvania Ave, south on 25th St to G St, and south on 26th St to F St, returning east on G and F Sts to 17th St (a short G St link joined 25th and 26th Sts). Second loop (approved Dec 7, 1916): 18th and 19th Sts south to Virginia Ave. Routes 80/82 ended here as 'Potomac Park' / 'Virginia Ave' (out 18th St, back 19th St) | D44: DC | E44: Capital Traction | F44: Capital Transit; D.C. Transit | G44: Electric (conduit) | H44: 1901 | I44: — | J44: — | K44: 1901 | L44: 80, 82 | M44: Sept 7, 1958 (routes 80 and 82 converted; still on Wagner's Aug 1958 map) | N44: 1958 | O44: Buses | P44: The 1910 Rand McNally map shows only the 1901 loops; the 1924 map shows track reaching Virginia Ave. The 18th St extension into Potomac Park was the District Commissioners' top recommendation in 1912. Identifying the Potomac Park terminal with the 1916 loop is an inference from the maps. 1912 map: West End loops on 25th and 26th Sts, G and F Sts; 26th St south of H St no longer exists, so that stretch is drawn straight. | Q44: WP-PennAve; TIN; MAP1910; MAP1924; MAP1942; TUN; MAP1958; MAP1912 | R44: 5.64 | S44: 0.14 | T44: L01 | U44: type=chronology name=West End loops / Potomac Park terminal network=Washington, D.C. streetcars operator=Capital Traction start_date=1901 end_date=1958 ref:streetcar_project=L56 ref=80;82 description=Later operators: Capital Transit; D.C. Transit source=WP-PennAve; TIN; MAP1910; MAP1924; MAP1942; TUN; MAP1958; MAP1912 Dated route relations in this chronology: 1901–1916: 11 ways; operator=Capital Traction; railway:traction=electric 1916–1934: 14 ways; operator=Capital Traction; railway:traction=electric 1934–1956: 14 ways; operator=Capital Transit; railway:traction=electric 1956–1958: 14 ways; operator=D.C. Transit; railway:traction=electric
A45: L57 | B45: McLean Gardens loop | C45: Turning loop off Wisconsin Ave at McLean Gardens | D45: DC | E45: Capital Transit | F45: D.C. Transit | G45: Electric | I45: — | J45: — | K45: — | L45: 30 | M45: Probably Jan 3, 1960 with route 30 (inferred) | N45: 1960 | O45: Buses | P45: Shown on Wagner's Aug 1958 trackage map; opening date not found. End date inferred from the route 30 conversion. | Q45: MAP1958 | R45: 0.71 | S45: 0 | T45: — | U45: type=chronology name=McLean Gardens loop network=Washington, D.C. streetcars operator=Capital Transit start_date=1943 end_date=1960 ref:streetcar_project=L57 start_date:edtf=1943~ ref=30 description=Later operators: D.C. Transit source=MAP1958 Dated route relations in this chronology: 1943–1956: 2 ways; operator=Capital Transit; railway:traction=horse 1956–1960: 2 ways; operator=D.C. Transit; railway:traction=horse
A46: L58 | B46: Louisiana Ave trackage (route 20 to Union Station) | C46: From Pennsylvania Ave via 1st St NW and Louisiana Ave toward Union Station | D46: DC | E46: Not identified | F46: Capital Transit | G46: Electric | I46: — | J46: — | K46: — | L46: 20 | M46: Aug 28, 1949 (Tundria) | N46: 1949 | O46: Route 20 rerouted | P46: Only source for the closing date is Tundria's list of 1946–58 abandonments. Opening date not found. | Q46: TUN | R46: 0.47 | S46: 0.11 | T46: L04, L22 | U46: type=chronology name=Louisiana Ave trackage (route 20 to Union Station) network=Washington, D.C. streetcars operator=Not identified start_date=1908 end_date=1949 ref:streetcar_project=L58 start_date:edtf=1908~ ref=20 description=Later operators: Capital Transit source=TUN Dated route relations in this chronology: 1908–1934: 5 ways; operator=Washington Railway & Electric; railway:traction=horse 1934–1949: 5 ways; operator=Capital Transit; railway:traction=horse
A47: L40 | B47: Washington & Great Falls Railway & Power Co. | C47: Wisconsin Ave & Bradley Lane along what is now Bradley Blvd to Great Falls, MD (10.66 mi) | D47: MD | E47: Washington & Great Falls Railway & Power Co. (operated by WRECo) | F47: — | G47: Electric | H47: 1913 | I47: — | J47: — | K47: 1913 | L47: — | M47: Feb 12, 1921 | N47: 1921 | O47: — | P47: The only line that actually reached Great Falls. | Q47: WPMD; MPD | R47: 16.16 | S47: 0 | T47: — | U47: type=chronology name=Washington & Great Falls Railway & Power Co. network=Washington, D.C. streetcars operator=Washington & Great Falls Railway & Power Co. (operated by WRECo) start_date=1913 end_date=1921 ref:streetcar_project=L40 source=WPMD; MPD Dated route relations in this chronology: 1913–1921: 1 ways; operator=Washington Railway & Electric; railway:traction=electric
A48: L41 | B48: Forest Glen line | C48: Georgia & Eastern Aves (end of Brightwood line) along Georgia Ave and Seminary Rd to the National Park Seminary, Forest Glen (2.9 mi) | D48: MD | E48: Washington, Woodside & Forest Glen Railway | F48: WRECo | G48: Electric | H48: 1897 | I48: — | J48: — | K48: 1895/1897 | L48: — (bus Y8/Z2) | M48: Dec 15, 1924 | N48: 1924 | O48: Bus | P48: Opened Nov 25, 1897. CRF gives electric 1895. | Q48: WPMD; CRF | R48: 4.13 | S48: 0.06 | T48: L12 | U48: type=chronology name=Forest Glen line network=Washington, D.C. streetcars operator=Washington, Woodside & Forest Glen Railway start_date=1897 end_date=1924 ref:streetcar_project=L41 description=Later operators: WRECo source=WPMD; CRF Dated route relations in this chronology: 1897–1902: 2 ways; operator=Washington, Woodside & Forest Glen Railway; railway:traction=electric 1902–1924: 2 ways; operator=Washington Railway & Electric; railway:traction=electric
A49: L42 | B49: 'Dinky Line' – Takoma to Sligo | C49: 4th & Butternut Sts NW via 4th St, Aspen St and Laurel St into Takoma Park to Wildwood / Glen Sligo Hotel; Carroll Ave extension to the Sanitarium (1918) | D49: DC/MD | E49: Baltimore & Washington Transit Co. | F49: Washington & Maryland Ry (1910/1914); Capital Traction (1916) | G49: Electric (1897) → abandoned c.1903–07 → gasoline cars (May 30, 1910) → storage battery → electric | H49: 1897 | I49: — | J49: — | K49: 1897 | L49: — (bus T2) | M49: 1927 | N49: 1927 | O49: Bus T2 (later Ride-On) | P49: Leased by Capital Traction May 2, 1918 (Wikipedia main article says owned 1916). The original resort line closed around 1904; the tracks were removed and later rebuilt. | Q49: WP; WPMD; MPD; CRF | R49: 2.74 | S49: 0 | T49: — | U49: type=chronology name='Dinky Line' – Takoma to Sligo network=Washington, D.C. streetcars operator=Baltimore & Washington Transit Co. start_date=1897 end_date=1927 ref:streetcar_project=L42 description=Later operators: Washington & Maryland Ry (1910/1914); Capital Traction (1916) source=WP; WPMD; MPD; CRF Dated route relations in this chronology: 1897–1916: 3 ways; operator=Baltimore & Washington Transit Co.; railway:traction=electric 1916–1927: 3 ways; operator=Capital Traction; railway:traction=electric
A50: L43 | B50: Kennedy Street / 3rd Street – Takoma line | C50: 3rd St NW and Kennedy St NW to 14th St & Colorado Ave (connection with 14th St line) | D50: DC | E50: Washington & Maryland Railway | F50: Capital Traction (1916); Capital Transit | G50: Electric | H50: 1910 | I50: — | J50: — | K50: 1910 | L50: — (bus J2 / K8) | M50: April 1936 | N50: 1936 | O50: Bus K8 | P50: Built between 1903 and 1917 (Wikipedia); CRF dates it 1910. | Q50: WP; CRF | R50: 3.46 | S50: 0 | T50: — | U50: type=chronology name=Kennedy Street / 3rd Street – Takoma line network=Washington, D.C. streetcars operator=Washington & Maryland Railway start_date=1910 end_date=1936 ref:streetcar_project=L43 description=Later operators: Capital Traction (1916); Capital Transit source=WP; CRF Dated route relations in this chronology: 1910–1916: 2 ways; operator=Washington & Maryland Railway; railway:traction=electric 1916–1934: 2 ways; operator=Capital Traction; railway:traction=electric 1934–1936: 2 ways; operator=Capital Transit; railway:traction=electric
A51: L44 | B51: 14th Street – Takoma line | C51: 14th St line branch to Takoma | D51: DC | E51: Capital Traction | F51: Capital Transit | G51: Electric | H51: 1910 | I51: — | J51: — | K51: 1910 | L51: 58 | M51: April 1936 (CRF); Wikipedia says the Takoma line converted by 1937 | N51: 1936 | O51: Bus K8 | Q51: CRF; WP | T51: Not drawn
A52: L45 | B52: East Washington Heights Traction | C52: Pennsylvania Ave SE from the Capitol to Barney Circle (1903), across the bridge to Randle Highlands at 27th St SE (1908), past 33rd St SE (1917) | D52: DC | E52: East Washington Heights Traction Railroad | F52: — | G52: Electric | H52: 1903 | I52: — | J52: — | K52: 1905 (CRF) | L52: — (bus C2) | M52: Dec 1, 1923 (first streetcar-to-bus conversion) | N52: 1923 | O52: Bus C2 / 32 / 34 | P52: Two streetcars, about one mile of track. The 1910 Rand McNally map shows the line crossing the Pennsylvania Ave bridge (the 1908 extension). The 1924 map may still show it because of plate lag. | Q52: WP; CRF | R52: 2.29 | S52: 0 | T52: — | U52: type=chronology name=East Washington Heights Traction network=Washington, D.C. streetcars operator=East Washington Heights Traction Railroad start_date=1903 end_date=1923 ref:streetcar_project=L45 source=WP; CRF Dated route relations in this chronology: 1903–1905: 1 ways; operator=East Washington Heights Traction Railroad; railway:traction=horse 1905–1917: 1 ways; operator=East Washington Heights Traction Railroad; railway:traction=electric 1917–1923: 2 ways; operator=East Washington Heights Traction Railroad; railway:traction=electric
A53: L46 | B53: Bladensburg Road line | C53: 15th & H Sts NE along Bladensburg Rd to Bladensburg (1910); battery-car extension to Berwyn Heights (1912) | D53: DC/MD | E53: Washington, Spa Spring & Gretta Railroad | F53: Washington Interurban Railway (1912) / Railroad (1916) | G53: Electric in DC; storage-battery cars in MD | H53: 1910 | I53: — | J53: — | K53: 1910 | L53: — (bus B2) | M53: Apr 22, 1923 (CRF); abandoned incrementally 1921–25 (NRHP) | N53: 1923 | O53: Bus B2 | P53: MD charter Feb 13, 1905; DC entry Feb 18, 1907. 2.89 mi in DC and 5.55 mi in MD. Not drawn on either the 1910 or the 1924 Rand McNally map. | Q53: WP; MPD; CRF | R53: 12.64 | S53: 0 | T53: — | U53: type=chronology name=Bladensburg Road line network=Washington, D.C. streetcars operator=Washington, Spa Spring & Gretta Railroad start_date=1910 end_date=1923 ref:streetcar_project=L46 description=Later operators: Washington Interurban Railway (1912) / Railroad (1916) source=WP; MPD; CRF Dated route relations in this chronology: 1910–1912: 1 ways; operator=Washington, Spa Spring & Gretta Railroad; railway:traction=electric 1912–1923: 2 ways; operator=Washington, Spa Spring & Gretta Railroad; railway:traction=electric
A54: L47 | B54: Massachusetts Avenue line | C54: Massachusetts Ave NW | D54: DC | E54: WRECo | F54: — | G54: Electric | H54: 1908 | I54: — | J54: — | K54: 1908 | L54: — (bus N2/N4) | M54: May 13, 1925 | N54: 1925 | O54: Bus N4 | Q54: CRF | T54: Not drawn
A55: L48 | B55: LeDroit Park line | C55: Belt Railway extension (1896): 4th & O NW north on 4th St to Florida Ave, then Harewood, Elm, Linden and Pomeroy Sts to 7th St, LeDroit Park; through-routed to the wharves by Washington Traction | D55: DC | E55: Belt Railway (1896 extension) | F55: WRECo; Capital Transit | G55: Horse → electric (1900) | H55: 1875 | I55: 1875 | J55: — | K55: 1900 | L55: — (bus G2) | M55: Jan 7, 1935 | N55: 1935 | O55: Bus G2 | P55: Drawn on the 1924 Rand McNally map (loop near Howard University and the ballpark). Map: ran into LeDroit Park via 3rd St, Elm St, 4th St and V St to Georgia Ave (1912 map). 1912 map: the LeDroit Park line reached Georgia Ave along W St. | Q55: MPD; CRF; LAWS | R55: 1.76 | S55: 0.16 | T55: L22, L32, L33 | U55: type=chronology name=LeDroit Park line network=Washington, D.C. streetcars operator=Belt Railway (1896 extension) start_date=1875 end_date=1935 ref:streetcar_project=L48 description=Later operators: WRECo; Capital Transit source=MPD; CRF; LAWS Dated route relations in this chronology: 1875–1896: 2 ways; operator=Belt Railway; railway:traction=horse 1896–1900: 4 ways; operator=Belt Railway; railway:traction=horse 1900–1912: 4 ways; operator=Belt Railway; railway:traction=electric 1912–1934: 4 ways; operator=Washington Railway & Electric; railway:traction=electric 1934–1935: 4 ways; operator=Capital Transit; railway:traction=electric
A56: L49 | B56: Key Bridge – Rosslyn line | C56: M St across the Francis Scott Key Bridge to the Rosslyn loop and W&OD terminal | D56: DC/VA | E56: Capital Traction | F56: Capital Transit | G56: Electric | H56: 1923 | I56: — | J56: — | K56: 1923 | L56: 10 (Rosslyn–Benning) | M56: Aug 26, 1956 (Wikipedia, CRF) or Dec 24, 1948 (Tundria): unresolved conflict | N56: 1956 | O56: Bus 38 | P56: Replaced W&OD service over the old Aqueduct Bridge. | Q56: WP; CRF; GDC; TUN | R56: 1.2 | S56: 0 | T56: — | U56: type=chronology name=Key Bridge – Rosslyn line network=Washington, D.C. streetcars operator=Capital Traction start_date=1923 end_date=1956 ref:streetcar_project=L49 ref=10 description=Later operators: Capital Transit source=WP; CRF; GDC; TUN Dated route relations in this chronology: 1923–1934: 5 ways; operator=Capital Traction; railway:traction=electric 1934–1956: 5 ways; operator=Capital Transit; railway:traction=electric
A57: L50 | B57: 14th St – U St – 11th St route | C57: Capital Transit 1936 through-route combining 14th St, U St and 11th St trackage | D57: DC | E57: Capital Transit | F57: D.C. Transit | G57: Electric | H57: 1936 | I57: — | J57: — | K57: 1936 | L57: 52 | M57: Jan 28, 1962 (CRF) | N57: 1962 | O57: Discontinued | Q57: CRF; WP | T57: Not drawn
A58: L51 | B58: Bureau of Engraving loop / Southwest government trackage | C58: 14th St SW to the Bureau of Engraving (service since at least 1895); underground loop at 14th & C Sts SW (1942); new track 1939–41 to government buildings southwest of the Mall | D58: DC | E58: WRECo predecessor; Capital Transit | F58: D.C. Transit | G58: Electric | H58: 1895 | I58: — | J58: — | K58: 1895 | L58: 50 | M58: Jan 28, 1962 | N58: 1962 | O58: Bus 50s | P58: Loop is now part of a parking and storage structure under 14th St SW. | Q58: WP; MPD | R58: 1.04 | S58: 1.04 | T58: L22, V01 | U58: type=chronology name=Bureau of Engraving loop / Southwest government trackage network=Washington, D.C. streetcars operator=WRECo predecessor; Capital Transit start_date=1895 end_date=1962 ref:streetcar_project=L51 ref=50 description=Later operators: D.C. Transit source=WP; MPD Dated route relations in this chronology: 1895–1902: 2 ways; operator=WRECo predecessor; railway:traction=electric 1902–1934: 2 ways; operator=Washington Railway & Electric; railway:traction=electric 1934–1956: 2 ways; operator=Capital Transit; railway:traction=electric 1956–1962: 2 ways; operator=D.C. Transit; railway:traction=electric
A59: V01 | B59: Washington, Alexandria & Mount Vernon line | C59: Mount Vernon – Alexandria – Arlington Junction – Long Bridge (Highway Bridge from Feb 12, 1906) – DC. DC route 1896: 14th & B via B St, 13½ St and E St to 14th St on Belt tracks. From 1902: 12th & D, 12th St, C St, 14th St | D59: VA/DC | E59: Washington, Alexandria & Mount Vernon Electric Railway | F59: Washington-Virginia Railway (1910) | G59: Electric (interurban) | H59: 1892 | I59: — | J59: — | K59: 1892 | L59: — | M59: Lost DC access Jan 17, 1932 | N59: 1932 | O59: Alexandria & Suburban / AB&W buses | P59: Alexandria–Mount Vernon service began 1892. | Q59: WP; WPVA | R59: 22.02 | S59: 1.09 | T59: L22, L51 | U59: type=chronology name=Washington, Alexandria & Mount Vernon line network=Washington, D.C. streetcars operator=Washington, Alexandria & Mount Vernon Electric Railway start_date=1892 end_date=1932 ref:streetcar_project=V01 description=Later operators: Washington-Virginia Railway (1910) source=WP; WPVA Dated route relations in this chronology: 1892–1896: 1 ways; operator=Washington, Alexandria & Mount Vernon Electric Railway; railway:traction=electric 1896–1932: 7 ways; operator=Washington, Alexandria & Mount Vernon Electric Railway; railway:traction=electric
A60: V02 | B60: Rosslyn branch (East Arlington) | C60: Arlington Junction – Mt. Vernon Junction – along Arlington Ridge Rd – Rosslyn (Aqueduct Bridge) | D60: VA | E60: Washington, Alexandria & Mount Vernon Electric Railway | F60: Washington-Virginia Railway | G60: Electric | H60: 1896 | I60: — | J60: — | K60: 1896 | L60: — | M60: Rosslyn–Mt. Vernon Jct discontinued May 1921 | N60: 1921 | O60: — | P60: Opened May 22, 1896. | Q60: WPVA | R60: 4.67 | S60: 0.02 | T60: V06 | U60: type=chronology name=Rosslyn branch (East Arlington) network=Washington, D.C. streetcars operator=Washington, Alexandria & Mount Vernon Electric Railway start_date=1896 end_date=1921 ref:streetcar_project=V02 description=Later operators: Washington-Virginia Railway source=WPVA Dated route relations in this chronology: 1896–1921: 6 ways; operator=Washington, Alexandria & Mount Vernon Electric Railway; railway:traction=electric
A61: V03 | B61: Nauck (Fort Myer) line | C61: Rosslyn south through Fort Myer (N. Lynn St, N. Meade St, McNair Rd) to Nauck near Four Mile Run | D61: VA | E61: Washington, Arlington & Falls Church Railway | F61: Washington-Virginia; Arlington & Fairfax (1927) | G61: Horse (Oct 1892, Rosslyn–Fort Myer Gate) → electric | H61: 1892 | I61: 1892 | J61: — | K61: — | L61: — | M61: Not stated | O61: — | P61: Electrification year not documented; drawn as electric from 1896, when the company opened its electric Fairfax line. | Q61: WPVA | R61: 5.49 | S61: 0 | T61: — | U61: type=chronology name=Nauck (Fort Myer) line network=Washington, D.C. streetcars operator=Washington, Arlington & Falls Church Railway start_date=1892 end_date=1932 ref:streetcar_project=V03 end_date:edtf=1932~ description=Later operators: Washington-Virginia; Arlington & Fairfax (1927) source=WPVA Dated route relations in this chronology: 1892–1896: 5 ways; operator=Washington, Arlington & Falls Church Railway; railway:traction=horse 1896–1932: 5 ways; operator=Washington, Arlington & Falls Church Railway; railway:traction=electric
A62: V04 | B62: Fairfax line | C62: Rosslyn / DC via Clarendon, Ballston, Falls Church, Dunn Loring, Vienna and Oakton to the Fairfax County Courthouse | D62: VA/DC | E62: Washington, Arlington & Falls Church Railway | F62: Washington-Virginia (1910); Arlington & Fairfax (1927) | G62: Electric; later auto-railers | H62: 1896 | I62: — | J62: — | K62: 1896 | L62: — | M62: DC service ended Jan 17, 1932; company bankrupt 1939 | N62: 1932 | O62: Arlington & Fairfax Motor Transportation Co. | P62: Reached Falls Church 1897 and Fairfax Nov 28, 1904. Oakton station is on the NRHP. | Q62: WP; WPVA | R62: 22.21 | S62: 0 | T62: — | U62: type=chronology name=Fairfax line network=Washington, D.C. streetcars operator=Washington, Arlington & Falls Church Railway start_date=1896 end_date=1932 ref:streetcar_project=V04 description=Later operators: Washington-Virginia (1910); Arlington & Fairfax (1927) source=WP; WPVA Dated route relations in this chronology: 1896–1904: 2 ways; operator=Washington, Arlington & Falls Church Railway; railway:traction=electric 1904–1932: 3 ways; operator=Washington, Arlington & Falls Church Railway; railway:traction=electric
A63: V05 | B63: North Arlington branch | C63: Clarendon – Clarendon Blvd / Fairfax Dr / N. Lynn St – Rosslyn | D63: VA | E63: Washington, Arlington & Falls Church Railway | F63: Washington-Virginia; Arlington & Fairfax | G63: Electric | I63: — | J63: — | K63: — | L63: — | M63: Rosslyn terminal removed late 1939 | N63: 1939 | O63: — | P63: Roughly follows today's Orange/Silver Metro alignment. | Q63: WPVA | R63: 2.85 | S63: 0 | T63: — | U63: type=chronology name=North Arlington branch network=Washington, D.C. streetcars operator=Washington, Arlington & Falls Church Railway start_date=1906 end_date=1939 ref:streetcar_project=V05 start_date:edtf=1906~ description=Later operators: Washington-Virginia; Arlington & Fairfax source=WPVA Dated route relations in this chronology: 1906–1939: 6 ways; operator=Washington, Arlington & Falls Church Railway; railway:traction=horse
A64: V06 | B64: South Arlington branch (Clarendon Cutoff) | C64: Clarendon southeast along Washington Blvd to Mt. Vernon Junction and Arlington Junction | D64: VA | E64: Washington, Arlington & Falls Church Railway | F64: Washington-Virginia; Arlington & Fairfax | G64: Electric | H64: 1907 | I64: — | J64: — | K64: 1907 | L64: — | M64: Not stated | O64: — | Q64: WPVA | R64: 5.16 | S64: 0.02 | T64: V02 | U64: type=chronology name=South Arlington branch (Clarendon Cutoff) network=Washington, D.C. streetcars operator=Washington, Arlington & Falls Church Railway start_date=1907 end_date=1932 ref:streetcar_project=V06 end_date:edtf=1932~ description=Later operators: Washington-Virginia; Arlington & Fairfax source=WPVA Dated route relations in this chronology: 1907–1932: 6 ways; operator=Washington, Arlington & Falls Church Railway; railway:traction=electric
A65: V07 | B65: Great Falls & Old Dominion (W&OD Great Falls Division) into Georgetown | C65: Across the Aqueduct Bridge on a single track to a station at 36th St south of Prospect St (next to the Georgetown Car Barn) | D65: VA/DC | E65: Great Falls & Old Dominion Railroad | F65: Washington & Old Dominion Railway (1912) | G65: Electric (interurban) | H65: 1906 | I65: — | J65: — | K65: 1906 | L65: — | M65: 1923 (replaced by Capital Traction's Key Bridge service) | N65: 1923 | O65: Capital Traction Rosslyn line | P65: Authorized Jan 29, 1903; trial runs from Georgetown Mar 1906; scheduled service July 3, 1906. | Q65: TIN; WP-GFOD; MPD | R65: 22.07 | S65: 0.03 | T65: L39 | U65: type=chronology name=Great Falls & Old Dominion (W&OD Great Falls Division) into Georgetown network=Washington, D.C. streetcars operator=Great Falls & Old Dominion Railroad start_date=1906 end_date=1923 ref:streetcar_project=V07 description=Later operators: Washington & Old Dominion Railway (1912) source=TIN; WP-GFOD; MPD Dated route relations in this chronology: 1906–1923: 3 ways; operator=Great Falls & Old Dominion Railroad; railway:traction=electric
A66: V08 | B66: Washington, Baltimore & Annapolis Electric Railway | C66: Terminal at 15th & H Sts NE, over Benning Rd streetcar tracks and the Benning Rd bridge to Deanwood, then its own line to Baltimore and Annapolis | D66: DC/MD | E66: Washington, Baltimore & Annapolis Electric Railway | F66: — | G66: Electric interurban | H66: 1908 | I66: — | J66: — | K66: 1908 | L66: — | M66: 1935 | N66: 1935 | O66: — | P66: Main access to Suburban Gardens amusement park. | Q66: WP; MPD | R66: 10.26 | S66: 3.91 | T66: L16, L17 | U66: type=chronology name=Washington, Baltimore & Annapolis Electric Railway network=Washington, D.C. streetcars operator=Washington, Baltimore & Annapolis Electric Railway start_date=1908 end_date=1935 ref:streetcar_project=V08 source=WP; MPD Dated route relations in this chronology: 1908–1935: 6 ways; operator=Washington, Baltimore & Annapolis Electric Railway; railway:traction=electric

Sheet Track Ways
A1: Way | B1: Way id | C1: Length (m) | D1: start_date | E1: end_date | F1: Lines (route relations) | G1: Line names | H1: Shared | I1: Company families | J1: Way tags (OHM) | K1: Use by line (years)
A2: W028 | B2: 100028 | C2: 2922 | D2: 1898 | E2: 1949 | F2: L16, V08 | G2: Benning Road – Kenilworth branch; Washington, Baltimore & Annapolis Electric Railway | H2: Yes | I2: Independent / WRECo family | J2: railway=tram gauge=1435 start_date=1898 end_date=1949 | K2: L16 1898–1949; V08 1908–1935
A3: W410 | B3: 100422 | C3: 1040 | D3: 1898 | E3: 1949 | F3: L16, L17 | G3: Benning Road – Kenilworth branch; Seat Pleasant branch | H3: Yes | I3: WRECo family | J3: railway=tram gauge=1435 start_date=1898 end_date=1949 | K3: L16 1898–1949; L17 1900–1949
A4: W071 | B4: 100071 | C4: 945 | D4: 1872 | E4: 1935 | F4: L08, L18 | G4: 4th Street NW/SW line; Anacostia & Potomac River Railroad main line | H4: Yes | I4: WRECo family | J4: railway=tram gauge=1435 start_date=1872 end_date=1935 | K4: L08 1872–1935; L18 1900–1935
A5: W075 | B5: 100075 | C5: 869 | D5: 1875 | E5: 1962 | F5: L22, L51, V01 | G5: Belt Railway loop; Bureau of Engraving loop / Southwest government trackage; Washington, Alexandria & Mount Vernon line | H5: Yes | I5: Virginia / WRECo family | J5: railway=tram gauge=1435 start_date=1875 end_date=1962 | K5: L22 1875–1933; L51 1895–1962; V01 1896–1932
A6: W079 | B6: 100079 | C6: 819 | D6: 1875 | E6: 1961 | F6: L19, L22 | G6: 11th Street line; Belt Railway loop | H6: Yes | I6: WRECo family | J6: railway=tram gauge=1435 start_date=1875 end_date=1961 | K6: L19 1875–1961; L22 1875–1933
A7: W084 | B7: 100084 | C7: 786 | D7: 1872 | E7: 1935 | F7: L08, L18 | G7: 4th Street NW/SW line; Anacostia & Potomac River Railroad main line | H7: Yes | I7: WRECo family | J7: railway=tram gauge=1435 start_date=1872 end_date=1935 | K7: L08 1872–1935; L18 1888–1935
A8: W089 | B8: 100089 | C8: 762 | D8: 1862 | E8: 1960 | F8: L02, L22 | G8: 7th Street line; Belt Railway loop | H8: Yes | I8: Capital Traction family / WRECo family | J8: railway=tram gauge=1435 start_date=1862 end_date=1960 | K8: L02 1862–1960; L22 1875–1933
A9: W125 | B9: 100125 | C9: 540 | D9: 1862 | E9: 1962 | F9: L01, L02 | G9: Pennsylvania Avenue line (Georgetown–Navy Yard); 7th Street line | H9: Yes | I9: Capital Traction family | J9: railway=tram gauge=1435 start_date=1862 end_date=1962 | K9: L01 1862–1962; L02 1941–1960
A10: W129 | B10: 100129 | C10: 532 | D10: 1862 | E10: 1962 | F10: L01, L32 | G10: Pennsylvania Avenue line (Georgetown–Navy Yard); Florida Avenue / 8th Street extension | H10: Yes | I10: Capital Traction family | J10: railway=tram gauge=1435 start_date=1862 end_date=1962 | K10: L01 1862–1962; L32 1908–1962
A11: W138 | B11: 100138 | C11: 501 | D11: 1889 | E11: 1958 | F11: L25, L26 | G11: Glenwood Cemetery extension; North Capitol Street / Brookland line | H11: Yes | I11: WRECo family | J11: railway=tram gauge=1435 start_date=1889 end_date=1958 | K11: L25 1889–1894; L26 1890–1958
A12: W012 | B12: 100012 | C12: 495 | D12: 1898 | E12: 1949 | F12: L16, L17, V08 | G12: Benning Road – Kenilworth branch; Seat Pleasant branch; Washington, Baltimore & Annapolis Electric Railway | H12: Yes | I12: Independent / WRECo family | J12: railway=tram gauge=1435 start_date=1898 end_date=1949 | K12: L16 1898–1949; L17 1900–1949; V08 1908–1935
A13: W143 | B13: 100143 | C13: 494 | D13: 1898 | E13: 1949 | F13: L16, V08 | G13: Benning Road – Kenilworth branch; Washington, Baltimore & Annapolis Electric Railway | H13: Yes | I13: Independent / WRECo family | J13: railway=tram gauge=1435 start_date=1898 end_date=1949 | K13: L16 1898–1949; V08 1908–1935
... A428: W238 | B428: 100240 | C428: 2 | D428: 1894 | E428: 1908 | F428: L55 | G428: City & Suburban – Stanton Square / C & D St NE loop | H428: No | I428: WRECo family | J428: railway=tram gauge=1435 start_date=1894 end_date=1908 | K428: L55 1894–1908

Sheet Track Nodes
A1: Node id | B1: railway | C1: Latitude | D1: Longitude | E1: start_date | F1: end_date | G1: Node tags (OHM)
A2: 1633 | B2: railway_crossing | C2: 38.893582 | D2: -77.011322 | E2: 1862 | F2: 1949 | G2: railway=railway_crossing start_date=1862 end_date=1949
A3: 845 | B3: railway_crossing | C3: 38.900222 | D3: -77.031949 | E3: 1865 | F3: 1961 | G3: railway=railway_crossing start_date=1865 end_date=1961
A4: 1186 | B4: railway_crossing | C4: 38.897291 | D4: -77.021919 | E4: 1865 | F4: 1960 | G4: railway=railway_crossing start_date=1865 end_date=1960
A5: 1486 | B5: railway_crossing | C5: 38.899819 | D5: -77.021913 | E5: 1865 | F5: 1960 | G5: railway=railway_crossing start_date=1865 end_date=1960
A6: 1459 | B6: railway_crossing | C6: 38.900041 | D6: -77.030281 | E6: 1870 | F6: 1949 | G6: railway=railway_crossing start_date=1870 end_date=1949
A7: 1468 | B7: railway_crossing | C7: 38.902108 | D7: -77.021913 | E7: 1870 | F7: 1949 | G7: railway=railway_crossing start_date=1870 end_date=1949
A8: 1430 | B8: railway_crossing | C8: 38.897281 | D8: -77.023973 | E8: 1872 | F8: 1933 | G8: railway=railway_crossing start_date=1872 end_date=1933
A9: 1476 | B9: railway_crossing | C9: 38.899819 | D9: -77.023967 | E9: 1872 | F9: 1933 | G9: railway=railway_crossing start_date=1872 end_date=1933
A10: 1508 | B10: railway_crossing | C10: 38.8936 | D10: -77.010526 | E10: 1872 | F10: 1961 | G10: railway=railway_crossing start_date=1872 end_date=1961
A11: 1111 | B11: railway_crossing | C11: 38.901171 | D11: -77.027038 | E11: 1875 | F11: 1949 | G11: railway=railway_crossing start_date=1875 end_date=1949
A12: 1223 | B12: railway_crossing | C12: 38.908572 | D12: -77.023967 | E12: 1875 | F12: 1933 | G12: railway=railway_crossing start_date=1875 end_date=1933
A13: 1224 | B13: railway_crossing | C13: 38.908572 | D13: -77.021919 | E13: 1875 | F13: 1933 | G13: railway=railway_crossing start_date=1875 end_date=1933
... A198: 610 | B198: switch | C198: 38.938891 | D198: -77.074675 | E198: 1943 | F198: 1960 | G198: railway=switch start_date=1943 end_date=1960

Sheet Chronology
A1: Year | B1: Date | C1: Line ID | D1: Line | E1: Event | F1: Sources
A2: 1862 | B2: May 17, 1862 | C2: L01 | D2: Pennsylvania Avenue line (Georgetown–Navy Yard) | E2: Congress incorporates the Washington & Georgetown Railroad, authorizing three horsecar lines. | F2: WP-W&G; TIN
A3: 1862 | B3: July 29, 1862 | C3: L01 | D3: Pennsylvania Avenue line (Georgetown–Navy Yard) | E3: First car runs on Pennsylvania Ave from the Capitol to the White House / State Dept. | F3: WP-PennAve; WP-W&G
A4: 1862 | B4: Aug 12, 1862 | C4: L01 | D4: Pennsylvania Avenue line (Georgetown–Navy Yard) | E4: Line extended west to Washington Circle. | F4: WP-PennAve
A5: 1862 | B5: Aug 18, 1862 | C5: L01 | D5: Pennsylvania Avenue line (Georgetown–Navy Yard) | E5: Line extended to Georgetown (Bridge & High Sts, now M St & Wisconsin Ave). | F5: WP-PennAve
A6: 1862 | B6: Oct 2, 1862 | C6: L01 | D6: Pennsylvania Avenue line (Georgetown–Navy Yard) | E6: Line extended east to the Navy Yard gate via A St S, Pennsylvania Ave and 8th St SE; full Georgetown–Navy Yard service begins. | F6: WP-PennAve; TIN
A7: 1862 | B7: Nov 15, 1862 | C7: L02 | D7: 7th Street line | E7: 7th Street line opens from N St NW to the Potomac River. | F7: WP-W&G
A8: 1862 | B8: Nov 15, 1862 | C8: L03 | D8: 14th Street line | E8: 14th St branch opens (White House – New York Ave – 14th St to Florida Ave); W&G article says 'by 1870'. | F8: WP-14th; MPD
A9: 1863 | B9: 1863 | C9: L02 | D9: 7th Street line | E9: Extended north to Boundary St (Florida Ave). | F9: WP-W&G; WP
A10: 1864 | B10: June 30, 1864 | C10: L03 | D10: 14th Street line | E10: Law permits the line to continue north of Boundary St. | F10: WP-14th
A11: 1864 | B11: July 1, 1864 | C11: L05 | D11: Metropolitan main line (Capitol–War Dept; later F St/D St line) | E11: Metropolitan Railroad chartered. | F11: TIN; WP-Metro
A12: 1865 | B12: Jan 1865 | C12: L05 | D12: Metropolitan main line (Capitol–War Dept; later F St/D St line) | E12: First lines complete: Capitol to 14th & I Sts NW, and H St NW from Massachusetts Ave to 17th St. | F12: MPD; WP-Metro
A13: 1865 | B13: 1865 | C13: L05 | D13: Metropolitan main line (Capitol–War Dept; later F St/D St line) | E13: Two-horse cars replaced by one-horse cars. | F13: WP-Metro
... A234: 1962 | B234: Jan 28, 1962 | C234: L51 | D234: Bureau of Engraving loop / Southwest government trackage | E234: Streetcar service ends; replaced by Bus 50s. | F234: WP; MPD; Lines sheet

Sheet 1905 Franchise Laws
A1: Built routes from 'Laws Relating to Street-Railway Franchises in the District of Columbia' (1905 recompilation)
A2: Transcribed from the Internet Archive OCR of the 1905 edition. Street names are as written in the law (e.g., 'old Sixteenth St' is now Mount Pleasant St). Only acts whose routes were built are listed; where only part of an authorized route was built, the route text is trimmed to that part. Dates marked c. were illegible in the OCR and are estimated from the Statutes at Large citation.
A3: Act date | B3: Year | C3: Company | D3: Act | E3: Authorized route (as written in the law) | F3: Built? | G3: Line ID | H3: Notes
A4: May 17, 1862 | B4: 1862 | C4: Washington & Georgetown RR | D4: Charter | E4: Bridge St (M St) from High St (Wisconsin Ave), Georgetown, across the Rock Creek 'tubular' bridge to Pennsylvania Ave; Pennsylvania Ave to 15th St; 15th St south back to Pennsylvania Ave; to the foot of the Capitol grounds, around their southern boundary to Pennsylvania Ave SE; to 8th St E (Garrison St) and south to the Navy Yard gate. Lateral along the Capitol's east front, then A St to the B&O depot and 1st St W back to Pennsylvania Ave. Branch on 7th St W from Boundary St to Pennsylvania Ave and the Potomac. Branch from Boundary St down 14th St W and New York Ave to Pennsylvania Ave. | F4: Built | G4: L01; L02; L03; L04 | H4: Horse power; 5-cent fare.
A5: June 30, 1864 | B5: 1864 | C5: Washington & Georgetown RR | D5: Amendment | E5: Extensions of the 7th St and 14th St lines north beyond Boundary St into Washington County. | F5: Built (route trimmed to the built portion) | G5: L02; L03
A6: Mar 3, 1875 | B6: 1875 | C6: Washington & Georgetown RR | D6: Pennsylvania Ave paving act | E6: Track must leave the Washington Aqueduct bridge over Rock Creek; relaid on 26th St from Pennsylvania Ave to M St, then M St into Georgetown to meet the Bridge St tracks. | F6: Built | G6: L01 | H6: Reversed in 1916 when cars returned to the rebuilt Pennsylvania Ave bridge.
A7: Mar 3, 1875 | B7: 1875 | C7: Washington & Georgetown RR | D7: Amendment | E7: 7th St W down Water St to P St S, then P St to the west side of the Arsenal gate, sharing A&PR track on Water St. | F7: Built | G7: L02
A8: Aug 23, 1894 | B8: 1894 | C8: Washington & Georgetown RR | D8: Sec. 3 of W&GF amendment | E8: Build a passenger station at the Aqueduct Bridge and extend M St tracks to at least 120 ft west of 35th St into it; switching on M St to cease. | F8: Built (Georgetown Car Barn, 1897) | G8: L01
A9: July 1, 1864 | B9: 1864 | C9: Metropolitan RR | D9: Charter | E9: Built portion: from the Capitol to 14th & I Sts NW and on toward the War Department, with the H St NW line from Massachusetts Ave to 17th St. | F9: Built (route trimmed to the built portion) | G9: L05; L06 | H9: Cars required every 4 minutes Capitol–B&O depot–departments–Circle.
A10: Mar 3, 1865 | B10: 1865 | C10: Metropolitan RR | D10: Amendment | E10: 4½ St W from D St N to the Arsenal gate; A St N and 1st St E to East Capitol St, then East Capitol St to 9th St E. | F10: Built (route trimmed to the built portion) | G10: L08; L09 | H10: 8-cent fare.
A11: July 13, 1868 | B11: 1868 | C11: Connecticut Avenue & Park Ry | D11: Charter | E11: 17th St & Pennsylvania Ave, 17th St to H St and Connecticut Ave, Connecticut Ave to P St (1873), extended to Boundary St (Florida Ave) by 1883. | F11: Built to P St (1873); to Florida Ave by 1883 | G11: L10
A12: Jan 19, 1872 | B12: 1872 | C12: Union RR (DC Legislative Assembly) | D12: Charter | E12: Connecticut Ave to P St, then P St across Rock Creek into Georgetown (the Metropolitan's P St / Georgetown line). | F12: Built as the Metropolitan's P St / Georgetown line | G12: L07
A13: Jan 19, 1872 | B13: 1872 | C13: Boundary & Silver Spring Ry (DC Legislative Assembly) | D13: Charter | E13: Boundary St & the Rockville Turnpike (7th St extended / Georgia Ave) north to Rock Creek Church Rd. | F13: Built to Rock Creek Church Rd by the Metropolitan | G13: L12 | H13: Tindall says the charter was forfeited.
A14: Aug 2, 1894 | B14: 1894 | C14: Metropolitan RR | D14: Motive power act | E14: Conversion to underground electric, conditioned on extending East Capitol St from 9th to 15th St E around both sides of Lincoln Square, and from 9th St W northwest on Florida Ave to 10th St W. | F14: Built (East Capitol to Lincoln Park, 1896) | G14: L09
A15: Feb 26, 1895 | B15: 1895 | C15: Metropolitan RR | D15: Amendment | E15: Single-track underground loop from 4½ & L SW down 4½ St to P St, west on P St to Water St, northwest on Water St to L St, east on L St back to 4½ St. Georgetown loop: P St from 35th to 36th St, south on 36th to Prospect, east on Prospect to 35th, north on 35th to O St. | F15: Built | G15: L07; L08 | H15: Georgetown loop served the Georgetown Car Barn.
A16: Feb 27, 1897 | B16: 1897 | C16: Metropolitan RR | D16: Extension | E16: From Connecticut & Florida Aves north along Columbia Rd to the west line of 18th St extended. | F16: Built | G16: L11
A17: June 6, 1900 | B17: 1900 | C17: Metropolitan RR | D17: Extension | E17: From 18th St & Columbia Rd east along Columbia Rd to 'old Sixteenth Street' (today's Mount Pleasant St), north to Park St; Columbia Rd to be widened to 100 ft and old 16th St to 85 ft. | F17: Built (Mount Pleasant service began June 6, 1900) | G17: L11 | H17: Tracks barred from the new 16th St roadway.
A18: Feb 18, 1875 | B18: 1875 | C18: Anacostia & Potomac River RR | D18: Congressional sanction | E18: From the north end of the Navy Yard bridge on 11th St E to M St S, then along M St to the Water St waterfront; across the bridge to Uniontown once it was rebuilt. | F18: Built (route trimmed to the built portion) | G18: L18
A19: Aug 1, 1888 | B19: 1888 | C19: Anacostia & Potomac River RR | D19: Amendment | E19: From M St S & 7th St E via 7th, G, 4th, E, Canal, B, 3rd Sts, Missouri Ave and 6th St to Center Market; from 7th & G SE along G St to 17th St E and E St to Congressional Cemetery; Nichols Ave to the Government Hospital for the Insane. | F19: Built (route trimmed to the built portion) | G19: L18
A20: June 4, 1900 | B20: 1900 | C20: A&PR / Capital Traction | D20: Extension act | E20: A&PR: underground line on 1st St E from E St S north to B St S, then west on B St to its tracks between 2nd and 3rd Sts W. Capital Traction: 1st & C NW east on C St to Delaware Ave with a loop around square 686 (Delaware Ave, B, 1st and C Sts NE); West End loops via 17th, G and 25th Sts and via 17th, F and 26th Sts, with a G St link between 25th and 26th. Capital Traction's C St NW tracks between 1st St and New Jersey Ave to be removed. | F20: Built (West End loops opened Mar 24, 1901) | G20: L01; L04; L18
A21: July 1, 1902 | B21: 1902 | C21: Anacostia & Potomac River RR | D21: Extension | E21: Eleventh St line extended by double track from 11th St & Florida Ave north along 11th St to Lydecker Ave. Cars may switch on old 16th St between Grant and Park Sts until the Metropolitan extends there. | F21: Built (became the route to 11th & Monroe) | G21: L19
A22: Mar 3, 1875 | B22: 1875 | C22: Capitol, North O Street & South Washington Ry (Belt) | D22: Charter | E22: 1st St W in front of the Capitol north to G St N; west on G St to 4th St W; 4th St to O St N; O St to 11th St W; south on 11th St to E St N; west on E St to 14th St W; south on 14th St to Ohio Ave; Ohio Ave to 12th St W; south on 12th St to Virginia Ave; southeast on Virginia Ave to Maryland Ave; northeast on Maryland Ave back to 1st St W. | F22: Built | G22: L22
A23: May 23, 1876 | B23: 1876 | C23: Belt Railway | D23: Amendment | E23: Extend on 4th and 11th Sts from O St to P St, with a single one-way track on P St between 4th and 11th Sts instead of double track on O St. | F23: Built | G23: L22
A24: c. 1881 (21 Stat. 414) | B24: 1881 | C24: Belt Railway | D24: Amendment | E24: 14th St from Ohio Ave to C St SW, east on C St to Virginia Ave. 11th St from P St north to Boundary St. 11th St from C St SW south to Water St, then east on Water St to M St S (new southern terminus). Bureau of Engraving fare to nearest junction 2¢. | F24: Built | G24: L19; L22
A25: June 10, 1896 | B25: 1896 | C25: Belt Railway | D25: Extension | E25: From 4th & O NW north on 4th St to Florida Ave, then Harewood, Elm, Linden and Pomeroy Sts to 7th St (LeDroit Park). | F25: Built (LeDroit Park line) | G25: L48 | H25: Horsepower barred on extensions.
A26: June 19, 1888 | B26: 1888 | C26: Eckington & Soldiers' Home Ry | D26: Charter | E26: New York Ave from 7th St NW to the Eckington area (3rd St and T St NE), with the 4th St NE extension toward Bunker Hill Rd (Michigan Ave) and a branch north toward the Soldiers' Home. | F26: Built (route trimmed to the built portion) | G26: L23; L24; L26
A27: c. 1890 (Sec. 12) | B27: 1890 | C27: Eckington & Soldiers' Home Ry | D27: Extension | E27: From New York Ave & 5th St south along 5th to G St NW, west on G St to 15th St NW (underground wires required). Cemetery branch on Lincoln Ave to the Glenwood Cemetery entrance. North Capitol St branch to the Soldiers' Home. | F27: Built | G27: L25; L26; L27
A28: July 5, 1892 | B28: 1892 | C28: Eckington & Soldiers' Home Ry | D28: Amendment | E28: Downtown loops from 5th & G NW via G St, 1st St and C St NW, New Jersey Ave, D St; G St across New Jersey Ave to North Capitol St and north to New York Ave; 5th St south to Louisiana Ave; C St NE around Stanton Square to 15th St NE, north to D St, west on D St to 4th St NE. Bunker Hill Rd extension toward Brooks station. | F28: Built in revised form (see 1894) | G28: L27; L55 | H28: Horse power banned; steam banned.
A29: Aug 23, 1894 | B29: 1894 | C29: Eckington & Soldiers' Home Ry | D29: Route rewritten | E29: 5th & G NW east on G St to New Jersey Ave & 1st St; south on 1st to C St NW; east on C St around Stanton Square and along C and D Sts NE to a turn at 13th St; G St to North Capitol St and north to New York Ave; 5th St south to Louisiana Ave, 6th St and B St NW to near 7th St. | F29: Built | G29: L27; L55
A30: June 27, 1898 | B30: 1898 | C30: Eckington & S.H. / Maryland & Washington | D30: Merger & relocation act | E30: E&SH buys the M&W and becomes the City & Suburban Railway. Track changes: single track moved from T & 3rd / R & 2nd NE to T and 2nd Sts; Eckington Pl–Florida Ave–New York Ave replaced by double track on 1st St NE; 5th St between New York Ave and G St widened to 45 ft; single track on C St NE between 1st and 4th Sts moved to D and 1st Sts. | F30: Built | G30: L23; L28
A31: c. 1902–03 (joint resolution) | B31: 1903 | C31: City & Suburban Ry | D31: Relocation | E31: Stanton Square track moved from the south to the north side (4th to 6th & C NE). Underground conduit on the Eckington loop (Eckington Pl, R St, 3rd St, T St, 2nd St). Double track on North Capitol St from T St to Michigan Ave and east on Michigan Ave, overhead trolley allowed until July 1, 1904 or paving. | F31: Built | G31: L23; L26; L55
A32: Aug 22, 1888 | B32: 1888 | C32: Georgetown & Tennallytown Ry | D32: Charter | E32: From the Potomac River near High St, along High St (Wisconsin Ave) to the Tennallytown road, then alongside that road (outside its limits) to the District line; power conduits may run under Water St. | F32: Built | G32: L36
A33: c. 1890 (26 Stat. 29) | B33: 1890 | C33: Georgetown & Tennallytown Ry | D33: Amendment | E33: Track to run in the Tennallytown road rather than beside it. | F33: Built | G33: L36
A34: Oct 18, 1888 | B34: 1888 | C34: Brightwood Ry | D34: Charter | E34: Brightwood Ave (Georgia Ave) from Boundary St to the District line; horse, cable or electric. | F34: Built | G34: L12
A35: c. July 1892 (27 Stat. 270) | B35: 1892 | C35: Brightwood Ry | D35: Amendment | E35: Overhead wires permitted. Must reach the District line within 12 months. Branch from west of the B&O on 5th St, Takoma Park, along 5th St to Umatilla St, west on Umatilla across Piney Branch Rd to Brightwood Ave; cars at least every 15 minutes. | F35: Built | G35: L12; L13
A36: Feb 27, 1893 | B36: 1893 | C36: Brightwood Ry | D36: Branch | E36: Overhead trolley branch from Rock Creek Church Rd & Richmond St (Petworth) west on Richmond St to Brightwood Ave; south on Brightwood Ave to Marshall St; west on Marshall St to Kenyon Ave; west on Kenyon to 14th St. | F36: Built, then ordered removed | G36: L53
A37: c. 1893–95 (date not legible) | B37: 1894 | C37: Brightwood Ry | D37: Abandonment order | E37: Must vacate its Kenyon and Marshall St track between 7th and 14th Sts and remove poles within one month; may re-equip it with underground electric within a year, or forfeit that part of the charter. | F37: Abandoned | G37: L53 | H37: $25/day fine for delay.
A38: May 28, 1896 | B38: 1896 | C38: Capital Ry | D38: Route rewritten | E38: Built portion: from the Navy Yard bridge along Nichols Ave to Congress Heights. | F38: Built (route trimmed to the built portion) | G38: L20
A39: c. 1897 | B39: 1897 | C39: Capital Ry | D39: Amendment | E39: Double overhead trolley allowed on the Navy Yard bridge (max 3.5 mph, wires in wooden trough); may adopt the Metropolitan-type conduit if its magnetic system is rejected. | F39: Built | G39: L20
A40: May 28, 1890 | B40: 1890 | C40: Rock Creek Ry | D40: Route change | E40: Connecticut & Florida Aves east on Florida to 18th St; north on 18th to Columbia Rd; across Columbia Rd through the Cliffbourne tract to Rock Creek; public iron bridge (≥50 ft wide); northwest through Woodley Park to Connecticut Ave extended; north to the District line. Also 18th & U east along U St to 14th St. | F40: Built | G40: L30; L31
A41: Mar 3, 1891 | B41: 1891 | C41: Rock Creek Ry | D41: Amendment | E41: May buy, lease or operate the Chevy Chase Land Co.'s Maryland line to Chevy Chase Lake. | F41: Built | G41: L30
A42: Apr 30, 1892 | B42: 1892 | C42: Rock Creek Ry | D42: Extension | E42: U St terminus extended along Florida Ave. | F42: Built (route trimmed to the built portion) | G42: L31
A43: June 2, 1900 | B43: 1900 | C43: Capital Traction | D43: Extension | E43: Double track from Pennsylvania Ave & 8th St SE east along Pennsylvania Ave to 15th St E, then a single-track loop on Pennsylvania Ave, the circle, K St and 15th St around square 1078. | F43: Built (1901) | G43: L01
A44: May 24, 1870 | B44: 1870 | C44: Columbia Ry | D44: Charter | E44: 15th St & New York Ave east along New York Ave to K St N; K St to Massachusetts Ave; Massachusetts Ave to H St N; H St to the Columbia turnpike gate. Option within 2 years along the Columbia Turnpike or other roads north or east; horse or dummy engines. | F44: Built | G44: L15 | H44: 6-cent fare.
A45: 1898 | B45: 1898 | C45: Columbia Ry | D45: Eastward extension | E45: From the Benning Rd terminus to the Anacostia shore, across on a wooden trestle, then via Race Course Rd and the Anacostia road toward the District's eastern corner (Seat Pleasant). | F45: Built (route trimmed to the built portion) | G45: L16; L17 | H45: No earth return; double trolley.
A46: June 18, 1898 | B46: 1898 | C46: East Washington Heights Traction RR | D46: Charter | E46: From the west approach to the Pennsylvania Ave bridge (Barney Circle) across the Anacostia and along Pennsylvania Ave extended toward Randle Highlands. | F46: Built (route trimmed to the built portion) | G46: L45
A47: July 1, 1902 | B47: 1902 | C47: East Washington Heights Traction RR | D47: Amendment | E47: May lay a single track across the Pennsylvania Ave bridge to Capital Traction's eastern terminus; must pay half the bridge upkeep. | F47: Built | G47: L45
A48: Aug 1, 1892 | B48: 1892 | C48: Maryland & Washington Ry | D48: Charter | E48: From where Rhode Island Ave extended meets 4th St NE, along Rhode Island Ave extended to the northeast District line; land acquired to be dedicated as Rhode Island Ave. | F48: Built | G48: L28
A49: Mar 2, 1895 | B49: 1895 | C49: Maryland & Washington Ry | D49: Amendment | E49: 130-ft right-of-way by condemnation along the Rhode Island Ave extension plan. Also west on Rhode Island Ave to North Capitol St, then south on North Capitol over Eckington tracks to F St. | F49: Built | G49: L28
A50: Aug 23, 1894 | B50: 1894 | C50: Washington, Alexandria & Mount Vernon Electric Ry | D50: Entry into DC | E50: B St between 7th and 8th Sts NW, west on B St to 13½ St, north to E St, west on E St to 14th St, then south on 14th St over Belt tracks to the Potomac (crossing by the Long Bridge). | F50: Built (route trimmed to the built portion) | G50: V01
A51: Aug 23, 1894 | B51: 1894 | C51: Washington & Great Falls Electric Ry | D51: Route rewritten | E51: From a station on the block bounded by Prospect, 35th, M and 36th Sts; west along Prospect St to about 38th St; on private land across Foxhall Rd; then the bluff and aqueduct-land route to Cabin John Creek. | F51: Built | G51: L39
A52: June 3, 1896 | B52: 1896 | C52: Washington & Great Falls Electric Ry | D52: Amendment | E52: Loop at 37th St & Prospect Ave, Georgetown. | F52: Built (route trimmed to the built portion) | G52: L39

Sheet Route Numbers 1936-62
A1: Route | B1: Termini | C1: Routing (1946 where known) | D1: Streetcar service ended | E1: Sources
A2: 10 | B2: Rosslyn – Kenilworth | C2: Rosslyn, Key Bridge, M St, Pennsylvania Ave, New York Ave, Mount Vernon Sq, H St, Benning Rd, Kenilworth Ave (1946) | D2: Kenilworth: May 1, 1949. Rosslyn: Aug 26, 1956 (Wikipedia/CRF) or Dec 24, 1948 (Tundria) | E2: WP-PennAve; CRF; TUN; MAP1942
A3: 12 | B3: New York Ave & 15th – Seat Pleasant | C3: New York Ave, H St, Benning Rd, then East Capitol St (Tundria) or Deane Ave/Dix St (Berman) to Seat Pleasant | D3: May 1, 1949 | E3: CRF; TUN; MAP1942
A4: 20 | B4: Cabin John – Union Station | C4: Cabin John, Glen Echo, Palisades, M St, Pennsylvania Ave, 1st St NW, Louisiana Ave (1946) | D4: Jan 3, 1960 (Louisiana Ave section Aug 28, 1949) | E4: WP-PennAve; CRF; TUN
A5: 22 | B5: Washington Circle | C5: Cabin John line short-turn (1936 map only) | D5: Not stated | E5: GDC
A6: 30 | B6: Friendship Heights – Barney Circle / 17th & K SE | C6: Wisconsin Ave, M St, Pennsylvania Ave, 7th St, Independence Ave, Pennsylvania Ave SE | D6: Jan 3, 1960 | E6: WP-PennAve; CRF; TUN; MAP1942
A7: 40 | B7: Mount Pleasant (Park Rd) – Lincoln Park / 15th & East Capitol | C7: Mount Pleasant St, Columbia Rd, Connecticut Ave, H St, 15th St, F St, 9th St, Pennsylvania Ave, C St NW, 1st St NE, East Capitol St | D7: Dec 3, 1961 (CRF). Wikipedia's Mount Pleasant Line article gives conflicting dates. | E7: CRF; TUN; MAP1942; MAP1958
A8: 42 | B8: Mount Pleasant (Park Rd) – 13th & C/D NE | C8: Mount Pleasant St, Columbia Rd, Connecticut Ave, H St, 15th St, F St, 5th St, G St, Union Station, Massachusetts Ave, Maryland Ave/D St out, C St/6th St back | D8: Dec 3, 1961 | E8: CRF; TUN; MAP1942; MAP1958
A9: 44 | B9: Connecticut Ave – Union Station | C9: Listed only on the 1936 map; not on the 1942, 1946 or 1958 maps | D9: Before 1942 (date not found) | E9: GDC
A10: 50 | B10: Decatur St / 14th St – Bureau of Engraving | C10: 14th St; underground loop at 14th & C SW (1942) | D10: Jan 28, 1962 | E10: WP-14th; CRF; TUN
A11: 52 | B11: 14th & Colorado – 6th & Pennsylvania Ave | C11: 14th St, U St, 11th St, then 11th St/E St out and 9th St/F St back, 9th St, Pennsylvania Ave | D11: Discontinued before 1962 (Wikipedia); CRF lists Jan 28, 1962 | E11: WP-14th; CRF; TUN
A12: 54 | B12: 14th & Colorado – Navy Yard | C12: 14th St, Pennsylvania Ave, 1st St NW, Independence Ave, Pennsylvania Ave SE, 8th St SE | D12: Jan 28, 1962 | E12: WP-PennAve; CRF; TUN
... A24: 92 | B24: National Zoo / Calvert St Bridge – Navy Yard | C24: Calvert St, 18th St, U St, Florida Ave, 8th St NE/SE | D24: Jan 28, 1962 | E24: WP-UStCH; CRF; TUN; MAP1942

Sheet CTC Route Table
A1: Streetcar lines and their bus conversion dates (chicagorailfan.com table, duplicates removed)
A2: Old route numbers: 1936 Capital Transit scheme. Numbers were grouped by tens clockwise from the west; letter codes are lines converted to buses before or around 1936. Blank year = source gives only a decade.
A3: Line (CRF name) | B3: Old route no. | C3: Pre-1933 operator | D3: Horse cars | E3: Cable cars | F3: Electric cars | G3: Converted to bus (M/D/YY) | H3: Year converted | I3: Successor bus route | J3: WMATA-era route no. (CRF key; parentheses = discontinued)
A4: Bladensburg | B4: B2 | C4: Washington Railway & Electric | F4: 1910 | G4: 4/22/23 | H4: 1923 | I4: — | J4: B2
A5: Naylor Gardens | B5: C2 | C5: East Washington Heights Traction | F5: 1905 | G5: 12/1/23 | H5: 1923 | I5: — | J5: 34
A6: Georgia Av.-Forest Glen | B6: Z2 | C6: Washington Railway & Electric | F6: 1895 | G6: 12/15/24 | H6: 1924 | I6: — | J6: Y8
A7: Massachusetts | B7: N2 | C7: Washington Railway & Electric | F7: 1908 | G7: 5/13/25 | H7: 1925 | I7: — | J7: N4
A8: Takoma-Old Bladensburg | B8: T2 | C8: Capital Traction | F8: 1897 | G8: 1927 | H8: 1927 | I8: Ride-On | J8: (T2)
A9: Anacostia-Congress Hts. | B9: A2 | C9: Washington Railway & Electric | F9: 1896 | G9: 6/16/35 | H9: 1935 | I9: — | J9: A2
A10: Connecticut-18th St. | B10: L2 | C10: Capital Traction | F10: 1892 | G10: 9/16/35 | H10: 1935 | I10: — | J10: L2
A11: Connecticut-Garrett Pk. | B11: L6 | C11: Capital Traction | F11: 1895 | G11: 9/16/35 | H11: 1935 | I11: Ride-On | J11: (L6)
A12: LeDroit Park | B12: G2 | C12: Washington Railway & Electric | D12: 1875 | F12: 1900 | G12: 1/7/35 | H12: 1935 | I12: — | J12: G2
A13: P St. | B13: G2 | C13: Washington Railway & Electric | D13: 1873 | F13: 1896 | G13: 6/16/35 | H13: 1935 | I13: — | J13: G2
A14: Wisconsin-Naval Hosp. | B14: T6 | C14: Washington Railway & Electric | F14: 1890 | G14: 8/4/35 | H14: 1935 | I14: Ride-On | J14: (T6)
A15: 14th St.-Takoma | B15: 58 | C15: Capital Traction | F15: 1910 | G15: 4/?/36 | H15: 1936 | I15: K8 | J15: (58)
A16: 3rd St.-Takoma | B16: J2 | C16: Capital Traction | F16: 1910 | G16: 4/?/36 | H16: 1936 | I16: Disc. | J16: (K8)
A17: Kennedy St. | B17: J2 | C17: Capital Traction | F17: 1910 | G17: 4/?/36 | H17: 1936 | I17: K8 | J17: (J2)
A18: Benning Rd. | B18: 10 | C18: Washington Railway & Electric | F18: 1898 | G18: 5/1/49 | H18: 1949 | I18: X2 | J18: (10)
A19: Benning-Benning Heights | B19: U8 | C19: Washington Railway & Electric | F19: 1898 | G19: 5/1/49 | H19: 1949 | I19: U8 | J19: (X4)
A20: Branchville-Beltsville | B20: 84 | C20: Washington Railway & Electric | F20: 1902 | G20: 7/31/49 | H20: 1949 | I20: Disc. | J20: (84)
A21: Capitol Hts.-Anacostia | B21: 12 | C21: Washington Railway & Electric | F21: 1898 | G21: 5/1/49 | H21: 1949 | I21: — | J21: V2
A22: Capitol Hts.-Navy Yard | B22: 12 | C22: Washington Railway & Electric | F22: 1898 | G22: 5/1/49 | H22: 1949 | I22: — | J22: V4
A23: H St. | B23: 10 | C23: Washington Railway & Electric | D23: 1871 | E23: 1895 | F23: 1899 | G23: 5/1/49 | H23: 1949 | I23: X2 | J23: (10)
A24: Kenilworth | B24: 10 | C24: Washington Railway & Electric | F24: 1898 | G24: 5/1/49 | H24: 1949 | I24: V8 | J24: (10)
A25: Seat Pleasant | B25: 12 | C25: Washington Railway & Electric | F25: 1898 | G25: 5/1/49 | H25: 1949 | I25: U8 | J25: (12)
A26: Ballston | B26: 10 | C26: Capital Traction | F26: 1923 | G26: 8/26/56 | H26: 1956 | I26: — | J26: 38
A27: Rosslyn | B27: 10 | C27: Capital Traction | F27: 1923 | G27: 8/26/56 | H27: 1956 | I27: 38 | J27: (10)
A28: College Park | B28: 82 | C28: Washington Railway & Electric | F28: 1897 | G28: 9/7/58 | H28: 1958 | I28: — | J28: 82
A29: North Capitol St. | B29: 80 | C29: Washington Railway & Electric | F29: 1890 | G29: 9/7/58 | H29: 1958 | I29: — | J29: 80
A30: R St.-Rhode Island | B30: 82 | C30: Washington Railway & Electric | F30: 1897 | G30: 9/7/58 | H30: 1958 | I30: — | J30: P6
A31: 7th St. | B31: 70 | C31: Capital Traction | D31: 1862 | E31: 1890 | F31: 1898 | G31: 1/3/60 | H31: 1960 | I31: — | J31: 70
A32: Cabin John | B32: 20 | C32: Washington Railway & Electric | F32: 1895 | G32: 1/3/60 | H32: 1960 | I32: Ride-On | J32: (20)
A33: Georgia Av. | B33: 70 | C33: Washington Railway & Electric | D33: 1873 | F33: 1890 | G33: 1/3/60 | H33: 1960 | I33: — | J33: 70
A34: Georgia Av.-Takoma | B34: 72 | C34: Washington Railway & Electric | F34: 1892 | G34: 1/3/60 | H34: 1960 | I34: 52/54 | J34: (72)
A35: Pennsylvania | B35: 30 | C35: Capital Traction | D35: 1862 | E35: 1892 | F35: 1898 | G35: 1/3/60 | H35: 1960 | I35: — | J35: 30
A36: Soldiers Home | B36: 74 | C36: Washington Railway & Electric | F36: 1893 | G36: 1/3/60 | H36: 1960 | I36: 60 | J36: (74)
A37: Upshur | B37: 74 | C37: Washington Railway & Electric | F37: 1893 | G37: 1/3/60 | H37: 1960 | I37: — | J37: 60
A38: Wisconsin | B38: 30 | C38: Washington Railway & Electric | F38: 1890 | G38: 1/3/60 | H38: 1960 | I38: — | J38: 31
A39: 11th St. | B39: 60 | C39: Washington Railway & Electric | D39: 1875 | F39: 1900 | G39: 12/3/61 | H39: 1961 | I39: 66 | J39: (60)
A40: Connecticut (south) | B40: 42 | C40: Washington Railway & Electric | D40: 1873 | F40: 1896 | G40: 12/3/61 | H40: 1961 | I40: — | J40: 42
A41: F St./D St. | B41: 42 | C41: Washington Railway & Electric | D41: 1865 | F41: 1896 | G41: 12/3/61 | H41: 1961 | I41: D6 | J41: (42)
A42: Mt. Pleasant | B42: 42 | C42: Washington Railway & Electric | F42: 1900 | G42: 12/3/61 | H42: 1961 | I42: — | J42: 42
A43: 14th St. | B43: 50 | C43: Capital Traction | D43: 1862 | E43: 1895 | F43: 1898 | G43: 1/28/62 | H43: 1962 | I43: Consol. | J43: (50)
A44: 14th St.-Pennsylvania | B44: 54 | C44: Capital Transit | F44: 1936 | G44: 1/28/62 | H44: 1962 | I44: — | J44: 54
A45: 14th St.-U St.-11th St. | B45: 52 | C45: Capital Transit | F45: 1936 | G45: 1/28/62 | H45: 1962 | I45: Disc. | J45: (52)
A46: East Capitol St. | B46: 40 | C46: Washington Railway & Electric | D46: 1872 | F46: 1896 | G46: 1/28/62 | H46: 1962 | I46: 96 | J46: (40)
A47: Florida Av./8th St. | B47: 92 | C47: Capital Traction | F47: 1908 | G47: 1/28/62 | H47: 1962 | I47: — | J47: 90
A48: New Jersey Av. | B48: 90 | C48: Capital Traction | F48: 1908 | G48: 1/28/62 | H48: 1962 | I48: — | J48: (90)
A49: U St. | B49: 92 | C49: Capital Traction | F49: 1892 | G49: 1/28/62 | H49: 1962 | I49: — | J49: 90
A50: 4th St. | B50: V2 | C50: Washington Railway & Electric | D50: 1872 | F50: 1895 | G50: 1930's | I50: M2 | J50: (V2)
A51: Capitol Hill-4th St. | B51: M2 | C51: Washington Railway & Electric | D51: 1872 | F51: 1895 | G51: 1930's | I51: Consol. | J51: (M2)
A52: NE 4th St. | B52: F4 | C52: Washington Railway & Electric | F52: 1888 | G52: 1920's | I52: G8 | J52: (F4)

Sheet Companies
A1: Company | B1: Chartered / incorporated | C1: Service began | D1: Ended / absorbed | E1: Successor | F1: Motive power | G1: Notes | H1: Sources
A2: Washington & Georgetown Railroad | B2: May 17, 1862 | C2: July 29, 1862 | D2: Sept 21, 1895 | E2: Capital Traction | F2: Horse / cable | G2: DC's first streetcar company. Lines: Pennsylvania Ave, 7th St, 14th St. | H2: WP; MPD
A3: Metropolitan Railroad | B3: July 1, 1864 | C3: 1864–65 | D3: Feb 4, 1902 | E3: WRECo (via Washington Traction & Electric) | F3: Horse / battery / electric | G3: Lines: F/D St, 9th St, P St–Georgetown, 4th St, East Capitol, Connecticut Ave, Georgia Ave. | H3: WP; MPD
A4: Connecticut Avenue & Park Railway | B4: July 13, 1868 | C4: April 1873 | D4: June 1874 | E4: Metropolitan | F4: Horse | G4: Connecticut Ave, 17th St & New York Ave to Florida Ave. | H4: WP; MPD
A5: Columbia Railway | B5: May 24, 1870 | C5: 1870 | D5: Feb 4, 1902 | E5: WRECo | F5: Horse / cable / electric | G5: H St NW/NE; Benning Rd branches (1898–1900). | H5: WP; MPD
A6: Union Railroad | B6: Jan 19, 1872 | C6: — | D6: 1872 | E6: Metropolitan | F6: Charter only | G6: Charter used for the Metropolitan's Georgetown/P St line. | H6: WP; MPD
A7: Boundary & Silver Spring Railway | B7: Jan 19, 1872 | C7: 1873 | D7: Dec 1872 (bought) | E7: Metropolitan | F7: Horse | G7: Georgia Ave charter. | H7: WP; MPD
A8: Anacostia & Potomac River Railroad | B8: 1870/1872 | C8: 1875 | D8: Aug 31, 1912 | E8: WRECo | F8: Horse / electric | G8: First line across the Anacostia; absorbed Belt (1898) and Capital Ry (1899). | H8: WP; MPD
A9: Capitol, North O Street & South Washington Ry (Belt Railway) | B9: Mar 3, 1875 | C9: 1875 | D9: 1898 | E9: Anacostia & Potomac River RR | F9: Horse / compressed air / electric | G9: Downtown belt loop. | H9: WP; MPD
A10: Eckington & Soldiers' Home Railway | B10: June 19, 1888 | C10: Oct 17, 1888 | D10: 1898 (renamed) | E10: City & Suburban Railway | F10: Electric (DC's first) | H10: WP; MPD
A11: Rock Creek Railway | B11: June 23, 1888 | C11: 1890 | D11: Sept 21, 1895 | E11: Capital Traction | F11: Electric | G11: Tied to the Chevy Chase Land Co. | H11: WP; MPD
A12: Georgetown & Tennallytown Railway | B12: Aug 22, 1888 | C12: Apr 25, 1890 | D12: 1926 (fully absorbed) | E12: WRECo | F12: Electric | H12: WP; MPD
A13: Brightwood Railway | B13: Oct 18, 1888 | C13: 1890 | D13: 1902 | E13: WRECo | F13: Pneumatic / horse / electric | H13: WP; MPD
A14: Glen Echo Railroad / Washington & Glen Echo RR | B14: 1889 | C14: June 1891 | D14: Oct 1902 | E14: Washington & Great Falls (part) | F14: Electric | H14: WPMD; MPD
A15: Tennallytown & Rockville Railroad | B15: 1890 | C15: 1890 | D15: — | E15: WRECo | F15: Electric | G15: Friendship Heights–Bethesda. | H15: WP; MPD
A16: Columbia & Maryland Ry / Berwyn & Laurel / Washington, Berwyn & Laurel | B16: 1892/1896 | C16: c.1899–1902 | D16: 1910 | E16: WRECo / City & Suburban | F16: Electric | G16: Reached Laurel in 1902. | H16: WPMD; MPD
A17: Maryland & Washington Railway | B17: Aug 1, 1892 (Congress) | C17: 1897 | D17: 1898 | E17: City & Suburban | F17: Electric | G17: Rhode Island Ave to Mount Rainier. | H17: WP; WPMD
A18: Washington & Great Falls Electric Railway | B18: July 28, 1892 | C18: 1895 | D18: 1902 (renamed) | E18: WRECo | F18: Electric | G18: Cabin John line; bought Washington Traction's holdings and became WRECo. | H18: WP; MPD
A19: Washington, Arlington & Falls Church Railway | B19: Feb 1891/1892 | C19: Oct 1892 | D19: Oct 17, 1910 | E19: Washington-Virginia Railway | F19: Horse / electric | G19: Fort Myer, Fairfax and Arlington lines. | H19: WP; WPVA
A20: Washington, Alexandria & Mount Vernon Electric Railway | B20: 1890 (as Alexandria & Fairfax) | C20: 1892 | D20: Oct 17, 1910 | E20: Washington-Virginia Railway | F20: Electric | G20: Entered DC over the Long Bridge (1896). | H20: WP; WPVA
A21: Baltimore & Washington Transit Co. ('Dinky Line') | B21: 1894/Apr 7, 1896 | C21: 1897 | D21: 1916 | E21: Washington & Maryland Ry → Capital Traction | F21: Electric / gasoline / battery | H21: WP; WPMD; MPD
A22: Capital Railway | B22: Mar 2, 1895 | C22: 1896 | D22: 1899 | E22: Anacostia & Potomac River RR | F22: Magnetic contact / electric | G22: Congress Heights. | H22: WP; MPD
A23: Capital Traction Company | B23: Mar 1, 1895 (authorized) | C23: Sept 21, 1895 | D23: Dec 1, 1933 | E23: Capital Transit | F23: Cable / electric | G23: Merger of Rock Creek and W&G. 53.70 miles of single track in DC in 1912. | H23: WP; MPD
A24: Chevy Chase Lake & Kensington Ry / Kensington Railway | B24: 1894 | C24: May 30, 1895 | D24: Sept 15, 1935 | E24: — | F24: Electric | G24: Leased by Capital Traction 1923–33. | H24: WPMD
A25: Washington, Woodside & Forest Glen Railway | B25: July 26, 1895 | C25: Nov 25, 1897 | D25: 1924 (bus) | E25: WRECo | F25: Electric | H25: WPMD; MPD
A26: Washington & Rockville Railway | B26: 1897 | C26: — | D26: 1935 (bus) | E26: WRECo | F26: Electric | H26: WP; MPD
A27: City & Suburban Railway of Washington | B27: 1898 | C27: 1898 | D27: 1926 (fully absorbed) | E27: WRECo | F27: Electric | G27: Former Eckington & Soldiers' Home. | H27: WP; MPD
A28: East Washington Heights Traction Railroad | B28: June 18, 1898 | C28: by 1903 | D28: Dec 1, 1923 (bus) | E28: — | F28: Electric | H28: WP; CRF
A29: Washington Traction & Electric Company | B29: June 5, 1899 | C29: — | D29: 1901–02 (foreclosure) | E29: WRECo | F29: Holding company | G29: Held most non-Capital Traction lines plus Potomac Electric. | H29: WP; MPD
A30: Great Falls & Old Dominion Railroad | B30: Jan 24, 1900 | C30: Entered DC 1903 | D30: 1912 (renamed) | E30: Washington & Old Dominion Railway | F30: Electric interurban | H30: WP; MPD
A31: Washington Railway & Electric Company (WRECo) | B31: 1902 (from W&GF) | C31: 1902 | D31: Dec 1, 1933 | E31: Capital Transit | F31: Electric | G31: The larger of the two big companies; also owned PEPCO. 108.95 miles of single track in DC in 1912. | H31: WP; MPD
A32: Washington, Spa Spring & Gretta RR / Washington Interurban | B32: Feb 13, 1905 (MD) | C32: 1910 | D32: 1921–25 (bus) | E32: — | F32: Electric / battery | H32: WP; MPD
A33: Washington, Baltimore & Annapolis Electric Railway | B33: 1899 | C33: 1908 | D33: 1935 | E33: — | F33: Electric interurban | H33: WP
A34: Washington-Virginia Railway | B34: 1910 | C34: 1910 | D34: 1927 (split at auction) | E34: Arlington & Fairfax; A&S | F34: Electric | H34: WP; WPVA
A35: Washington & Great Falls Railway & Power Co. | B35: May 29, 1912 | C35: July 2, 1913 | D35: Feb 12, 1921 | E35: — | F35: Electric | H35: WPMD
A36: Arlington & Fairfax Railway | B36: 1927 | C36: 1927 | D36: DC service ended Jan 17, 1932 | E36: A&F Motor Transportation | F36: Electric | H36: WP; WPVA
A37: Capital Transit Company | B37: 1933 | C37: Dec 1, 1933 | D37: Aug 14/15, 1956 (franchise revoked) | E37: D.C. Transit System | F37: Electric / bus | G37: Introduced numbered routes in 1936. | H37: WP; MPD
A38: D.C. Transit System, Inc. | B38: July 24, 1956 (franchise) | C38: 1956 | D38: Jan 28, 1962 (last streetcar) | E38: WMATA (buses, 1973) | F38: Electric / bus | G38: Required to go all-bus. | H38: WP; MPD

Sheet Maps
A1: Year | B1: Map | C1: Holder / publisher | D1: URL | E1: Access
A2: 1880 | B2: Horse-streetcar trackage (statistical map) | C2: Restored print from LOC statistical map series | D2: https://transitmap.net/store/product/1880-washington-dc/ | E2: Print for sale
A3: 1880 | B3: City of Washington statistical maps: Map No. 10, Street Railways (original of the 1880 print) | C3: Library of Congress | D3: https://www.loc.gov/resource/g3851fm.gct00015/?sp=11 | E3: LOC scan, free to reuse
A4: 1880 | B4: Map of the City of Washington showing the location of the Street Railways (modern redraw of the 1880 statistical map, Jake Berman, 2019) | C4: Jake Berman | D4: https://53studio.com/ | E4: Modern schematic
A5: 1888 | B5: DC Streetcar Network (1888) | C5: ArcGIS StoryMap 'How We Got Here' | D5: https://storymaps.arcgis.com/stories/d421c20521214832ac661b11a9ec3958 | E5: Online
A6: 1890–1962 | B6: All regional electric railway lines (composite) | C6: Greater Greater Washington / Wikimedia | D6: https://ggwash.org/view/29893/see-all-historic-dc-area-trolley-routes-on-one-map | E6: Online
A7: 1891 | B7: Street Railways, City of Washington | C7: transitmap.net | D7: https://transitmap.net/dc-streetcars-1891/ | E7: Online image
A8: 1891 | B8: Statistical map no. 10 showing the location of street railways (Engineer Dept. annual report maps) | C8: Library of Congress / Wikimedia Commons | D8: https://www.loc.gov/item/90685664/ | E8: LOC scan, free to reuse (sheet 10)
A9: 1892 | B9: Statistical map no. 10 showing the location of street railways | C9: Library of Congress | D9: https://www.loc.gov/item/87693024 | E9: LOC scan, free to reuse
A10: 1892 | B10: Map of Washington, D.C., and suburbs, showing the latest streets and all the new railway and street-car routes (F.L. Averill) | C10: Library of Congress / Wikimedia Commons | D10: https://commons.wikimedia.org/wiki/File:Map_of_Washington,_D.C.,_and_suburbs_-_showing_the_latest_streets_and_all_the_new_railway_and_street-car_routes_LOC_88693395.jpg | E10: Public domain scan
A11: 1893 | B11: Rand, McNally & Co.'s indexed atlas of the world: map of Washington, D.C. (business atlas map) | C11: Boston Public Library, Leventhal Map Center | D11: https://collections.leventhalmap.org/search/commonwealth:4m90f386r | E11: Free scan, no known restrictions
A12: 1895 | B12: Rand, McNally & Co. map of Washington, D.C. — georeferenced GeoTIFF (Maryland State Plane, NAD83) | C12: Harvard Map Collection (via NYU / MIT GeoData) | D12: https://geo.nyu.edu/catalog/harvard-g3850-1895-r3 | E12: Public GeoTIFF, already georeferenced
A13: 1900 | B13: Map of the city of Washington showing street railway lines (Eckert Litho, c.1900) | C13: Library of Congress | D13: https://www.loc.gov/item/87695722/ | E13: LOC scan, free to reuse
A14: 1904 | B14: Map of streetcar lines in Anacostia and surrounding districts | C14: Library of Congress | D14: https://www.loc.gov/item/91683221 | E14: LOC scan, free to reuse
A15: 1910 | B15: Rand McNally, Washington D.C. ('Electric Lines' in red) | C15: Library of Congress, call no. G3850 1910 .R3 | D15: https://www.loc.gov/item/87691460/ | E15: Link inferred from the number stamped on the scan; unverified
A16: 1912 | B16: Street railways of the District of Columbia with proposed extensions | C16: Library of Congress | D16: https://www.loc.gov/item/87695724 | E16: LOC scan, 2 sheets
A17: 1912 | B17: Senate Doc. 62-441, Enclosure 1: street railways of the District colored by company (22,483 x 18,622 px scan) | C17: GovInfo (Serial Set) | D17: https://www.govinfo.gov/app/details/SERIALSET-06181_00_00-076-0441-0000 | E17: Free PDF; Enclosure 1 is a 22,483 x 18,622 px color scan, colored by company
A18: 1918 | B18: PUC report (Senate Doc. 65-197): map of population density with street railway lines (police census Nov 1917), plus maps of downtown car stops | C18: GovInfo (Serial Set) | D18: https://www.govinfo.gov/app/details/SERIALSET-07323_00_00-002-0197-0000 | E18: Free PDF; foldout near p. 110
... A37: 1958 | B37: D.C. Transit System guide, street cars and bus lines (fold-out) | C37: eBay listing | D37: https://www.ebay.de/itm/146827621144 | E37: For sale
A38: c.1880 | B38: 'Early Street Railways' (modern GIS map on a present-day basemap) | C38: Source not identified | E38: Unknown; possible vector source

Sheet Research Notes
A1: Type | B1: Topic | C1: Detail
A2: Conflict | B2: 7th St cable start | C2: Apr 12, 1890 (Wikipedia W&G) vs May 12, 1890 (NRHP).
A3: Conflict | B3: 14th St opening | C3: Nov 15, 1862 (Wikipedia 14th St Line, NRHP) vs 'built by 1870' (Wikipedia W&G).
A4: Conflict | B4: Rock Creek suburban opening | C4: Sept 16, 1892 (Wikipedia Rock Creek) vs Sept 18, 1892 (NRHP).
A5: Conflict | B5: Glen Echo RR opening | C5: June 17, 1891 (Wikipedia MD article) vs July 10, 1891 (Georgetown-to-Rockville article).
A6: Conflict | B6: Union Station service | C6: June 24, 1908 (Wikipedia Capital Traction) vs Dec 6, 1908 (NRHP).
A7: Conflict | B7: Florida Ave/8th St builder | C7: Capital Traction (Tindall; Wikipedia Capital Traction article) vs WRECo (Wikipedia main article). Sheet uses Capital Traction.
A8: Conflict | B8: Washington & Maryland takeover | C8: Owned by Capital Traction 1916 (Wikipedia main) vs leased May 2, 1918 (Wikipedia B&W article, NRHP).
A9: Conflict | B9: A&PR incorporation | C9: May 5, 1870 (Wikipedia) vs May 19, 1872 under the 1870 general law (Tindall).
A10: Conflict | B10: Falls car barn demolition | C10: 1946 (Wikipedia WRECo) vs 1949 (NRHP).
A11: Conflict | B11: 9th St conversion | C11: 1933 (NRHP) vs 1936 (Ghosts of DC).
A12: Conflict | B12: Anacostia–Congress Heights | C12: June 16, 1935 (CRF bus date) vs July 16, 1935 last car (Wikipedia).
... A50: Scope | B50: Built only (version 7) | C50: Unbuilt charters, proposed extensions (including the 1912 Commissioners' recommendations), companies that never laid track, and routes that existed only on paper have been removed from every sheet. Where an act or charter was only partly built, only the built portion is described.

Sheet Sources
A1: Key | B1: Source | C1: URL | D1: Used for
A2: NRHP MPD | B2: Streetcar and Bus Resources of Washington, D.C., 1862-1962 (National Register Multiple Property Documentation Form, EHT Traceries, 2005) | C2: https://dcpreservation.org/wp-content/uploads/2021/11/Streetcar-and-Bus-MPD-FINAL-5.2.06.pdf | D2: Best narrative source: companies, extensions, motive power, car barns
A3: CRF | B3: Washington DC Transit Routes table (chicagorailfan.com) | C3: https://www.chicagorailfan.com/bcwasrtd.html | D3: Horse, cable and electric start years and bus conversion dates by line
A4: WP / WP-Main | B4: Wikipedia: Streetcars in Washington, D.C. | C4: https://en.wikipedia.org/wiki/Streetcars_in_Washington,_D.C. | D4: Company chronology, abandonment sequence, remnants
A5: WPMD | B5: Wikipedia: Streetcars in Washington, D.C., and Maryland | C5: https://en.wikipedia.org/wiki/Streetcars_in_Washington,_D.C.,_and_Maryland | D5: Maryland suburban lines
A6: WPVA | B6: Wikipedia: Northern Virginia trolleys | C6: https://en.wikipedia.org/wiki/Northern_Virginia_trolleys | D6: Virginia lines and branches
A7: GDC | B7: Ghosts of DC: The 1936 Capital Transit map | C7: https://ghostsofdc.org/2013/01/29/new-1936-streetcar-map/ | D7: 1936 route numbers and destinations
A8: GGW | B8: Greater Greater Washington: 1942 map; origin of Metrobus numbers | C8: https://ggwash.org/view/35308/check-out-this-1942-dc-bus-and-streetcar-map | D8: Route-number corridors
A9: TIN | B9: William Tindall, 'Beginnings of Street Railways in the National Capital,' Records of the Columbia Historical Society 21 (1918), pp. 24-86 | C9: https://archive.org/details/jstor-40067099 | D9: Charter routes, acts of Congress, company successions (full text read)
A10: GRAY | B10: V.H. Gray, 'Development of Street Railway Systems in Washington, D.C.' (Univ. of Maryland thesis, 1937) | C10: https://archive.org/details/DevelopmentOfStreetRailwaySystemsInWashingtonD.c.V.h.Gray | D10: Motive power, conduit construction, car types (little line detail)
A11: LAWS | B11: Laws Relating to Street-Railway Franchises in the District of Columbia (1896; 1905 ed.) | C11: https://archive.org/details/lawsrelatingtost00unit | D11: Primary source for authorized routes; read in full (see 1905 Franchise Laws sheet)
A12: WP-W&G | B12: Wikipedia: Washington and Georgetown Railroad | C12: https://en.wikipedia.org/wiki/Washington_and_Georgetown_Railroad
A13: WP-PennAve | B13: Wikipedia: Pennsylvania Avenue Line (Washington, D.C.) | C13: https://en.wikipedia.org/wiki/Pennsylvania_Avenue_Line_(Washington,_D.C.) | D13: Best line article: dated extensions, 1936 route list
A14: WP-14th | B14: Wikipedia: 14th Street Line (Washington, D.C.) | C14: https://en.wikipedia.org/wiki/14th_Street_Line_(Washington,_D.C.)
A15: WP-Metro | B15: Wikipedia: Metropolitan Railroad | C15: https://en.wikipedia.org/wiki/Metropolitan_Railroad
A16: WP-Columbia | B16: Wikipedia: Columbia Railway | C16: https://en.wikipedia.org/wiki/Columbia_Railway
A17: WP-A&PR | B17: Wikipedia: Anacostia and Potomac River Railroad | C17: https://en.wikipedia.org/wiki/Anacostia_and_Potomac_River_Railroad
A18: WP-Belt | B18: Wikipedia: Capitol, North O Street and South Washington Railway | C18: https://en.wikipedia.org/wiki/Capitol,_North_O_Street_and_South_Washington_Railway
A19: WP-RockCreek | B19: Wikipedia: Rock Creek Railway | C19: https://en.wikipedia.org/wiki/Rock_Creek_Railway
A20: WP-CapTraction | B20: Wikipedia: Capital Traction Company | C20: https://en.wikipedia.org/wiki/Capital_Traction_Company
A21: WP-WRECo | B21: Wikipedia: Washington Railway and Electric Company | C21: https://en.wikipedia.org/wiki/Washington_Railway_and_Electric_Company
A22: WP-G2R | B22: Wikipedia: Georgetown-to-Rockville streetcar service | C22: https://en.wikipedia.org/wiki/Georgetown-to-Rockville_streetcar_service
A23: WP-B&W | B23: Wikipedia: Baltimore and Washington Transit Company | C23: https://en.wikipedia.org/wiki/Baltimore_and_Washington_Transit_Company
A24: WP-GFOD | B24: Wikipedia: Great Falls and Old Dominion Railroad | C24: https://en.wikipedia.org/wiki/Great_Falls_and_Old_Dominion_Railroad
A25: WP-HSt / WP-UStCH | B25: Wikipedia: H Street Line; U Street–Congress Heights Line (Metrobus articles) | C25: https://en.wikipedia.org/wiki/H_Street_Line | D25: Used only where corroborated
A26: TUN | B26: Tundria (GS Tram Site): Washington 1946 streetcar routes and 1946–58 abandonments | C26: http://www.tundria.com/trams/USA/Washington-1946.php | D26: Street-by-street 1946 routings; secondary source
A27: MAP1880 | B27: City of Washington Statistical Map No. 10, Street Railways (1880) | C27: https://www.loc.gov/resource/g3851fm.gct00015/?sp=11 | D27: Map evidence
A28: MAP1910 | B28: Rand McNally, Washington D.C. (1910), LOC G3850 1910 .R3 | C28: https://www.loc.gov/item/87691460/ | D28: Map evidence (link unverified)
A29: MAP1924 | B29: Rand McNally standard map of Washington D.C., Commercial Atlas of America (1924) | C29: https://www.davidrumsey.com/ | D29: Map evidence
A30: MAP1912 | B30: Street railways of the District of Columbia with proposed extensions (Enclosure 1, Senate Doc. 62-441, March 20, 1912), with the Commissioners' report | C30: https://www.govinfo.gov/app/details/SERIALSET-06181_00_00-076-0441-0000 | D30: Map and text evidence
A31: MAP1942 | B31: Jake Berman, Capital Transit Street Car Lines, June 1, 1942 (2019 redraw) | C31: https://53studio.com/products/washington-dc-streetcar-system-map-june-1942 | D31: Map evidence (modern redraw)
A32: MAP1958 | B32: Charles Wagner, D.C. Transit trackage as of August 1958 | C32: https://transitmap.net/washington-dc-trackage-1958/ | D32: Map evidence
A33: Book | B33: LeRoy O. King, 100 Years of Capital Traction (1972) | D33: Cited heavily by the NRHP form; not consulted directly
A34: Book | B34: William Tindall, 'Beginnings of Street Railways in the National Capital,' Records of the Columbia Historical Society 21 (1918) | D34: Primary early-history source cited by Wikipedia
